[
    {
        "question": "FOSTERING :",
        "options": [
            {
                "option": "A.",
                "text": "Safeguarding"
            },
            {
                "option": "B.",
                "text": "Neglecting"
            },
            {
                "option": "C.",
                "text": "Ignoring"
            },
            {
                "option": "D.",
                "text": "Nurturing"
            }
        ],
        "answer": "Option D",
        "solution": "Answer & Solution Answer: Option D Solution: Safeguarding : a measure taken to protect someone or something or to prevent something undesirable. Neglecting : fail to care for properly. Ignoring : refuse to take notice of or acknowledge; disregard intentionally. Nurturing : care for and protect (someone or something) while they are growing. Fostering : encourage the development of (something, especially something desirable). Synonym of Fostering is Nurturing."
    },
    {
        "question": "PROPEL:",
        "options": [
            {
                "option": "A.",
                "text": "Drive"
            },
            {
                "option": "B.",
                "text": "Jettison"
            },
            {
                "option": "C.",
                "text": "Burst"
            },
            {
                "option": "D.",
                "text": "Acclimatize"
            },
            {
                "option": "E.",
                "text": "Modify"
            }
        ],
        "answer": "Option A",
        "solution": "Answer & Solution Answer: Option A Solution: Jettison : throw or drop (something) from an aircraft or ship. Burst : break open or apart suddenly and violently, especially as a result of an impact or internal pressure. Acclimatize : become accustomed to a new climate or new conditions, adjust Modify : make partial or minor changes to (something). Drive : propel or carry along by force in a specified direction. Propel : carry along by force in a specified direction. Synonym of Propel is Drive."
    },
    {
        "question": "MASSIVE:",
        "options": [
            {
                "option": "A.",
                "text": "Lump sum"
            },
            {
                "option": "B.",
                "text": "Strong"
            },
            {
                "option": "C.",
                "text": "Little"
            },
            {
                "option": "D.",
                "text": "Gaping"
            },
            {
                "option": "E.",
                "text": "Huge"
            }
        ],
        "answer": "Option E",
        "solution": "Answer & Solution Answer: Option E Solution: Lump sum : a single payment made at a particular time, as opposed to a number of smaller payments or installments. Strong : having the power to move heavy weights or perform other physically demanding tasks. Little : small in size, amount, or degree. Gaping : wide open. Huge : extremely large; enormous. Massive : exceptionally large. Synonym of Massive is Huge."
    },
    {
        "question": "STUMBLING BLOCK:",
        "options": [
            {
                "option": "A.",
                "text": "Argument"
            },
            {
                "option": "B.",
                "text": "Frustration"
            },
            {
                "option": "C.",
                "text": "Advantage"
            },
            {
                "option": "D.",
                "text": "Hurdle"
            },
            {
                "option": "E.",
                "text": "Fallout"
            }
        ],
        "answer": "Option D",
        "solution": "Answer & Solution Answer: Option D Solution: Argument : an exchange of diverging or opposite views, typically a heated or angry one. Frustration : the feeling of being upset or annoyed as a result of being unable to change or achieve something. Advantage : a condition or circumstance that puts one in a favourable or superior position. Fallout : the adverse results of a situation or action. Hurdle : one of a series of upright frames over which athletes in a race must jump. Stumbling Block : a circumstance that causes difficulty or hesitation. Synonym of Stumbling Block is Hurdle."
    },
    {
        "question": "DEFER :",
        "options": [
            {
                "option": "A.",
                "text": "Indifferent"
            },
            {
                "option": "B.",
                "text": "Defy"
            },
            {
                "option": "C.",
                "text": "Differ"
            },
            {
                "option": "D.",
                "text": "Postpone"
            }
        ],
        "answer": "Option D",
        "solution": "Answer & Solution Answer: Option D Solution: Indifferent : having no particular interest or sympathy, unconcerned. Defy : openly resist or refuse to obey. Differ : be unlike or dissimilar. Postpone : cause or arrange for (something) to take place at a time later than that first scheduled.Defer : put off (an action or event) to a later time; postpone. Synonym of Defer is Postpone."
    },
    {
        "question": "CEASE:",
        "options": [
            {
                "option": "A.",
                "text": "Begin"
            },
            {
                "option": "B.",
                "text": "Stop"
            },
            {
                "option": "C.",
                "text": "Create"
            },
            {
                "option": "D.",
                "text": "Dull"
            }
        ],
        "answer": "Option B",
        "solution": "Answer & Solution Answer: Option B Solution: Begin : perform or undergo the first part of (an action or activity). Create : bring (something) into existence. Dull : lacking interest or excitement. Stop : come to an end, cease to happen. Cease : come to an end, cease to happen. Synonym of Cease is Stop."
    },
    {
        "question": "PIOUS:",
        "options": [
            {
                "option": "A.",
                "text": "Religious"
            },
            {
                "option": "B.",
                "text": "Sympathetic"
            },
            {
                "option": "C.",
                "text": "Afraid"
            },
            {
                "option": "D.",
                "text": "Faithful"
            }
        ],
        "answer": "Option A",
        "solution": "Answer & Solution Answer: Option A Solution: Religious : relating to or believing in a religion. Sympathetic : feeling, showing, or expressing sympathy. Afraid : feeling fear or anxiety; frightened. Faithful : remaining loyal and steadfast. Pious : devoutly religious. Synonym of Pious is Religious."
    },
    {
        "question": "CANCEL:",
        "options": [
            {
                "option": "A.",
                "text": "Abolish"
            },
            {
                "option": "B.",
                "text": "Approve"
            },
            {
                "option": "C.",
                "text": "Allow"
            },
            {
                "option": "D.",
                "text": "Break"
            }
        ],
        "answer": "Option A",
        "solution": "Answer & Solution Answer: Option A Solution: Approve : officially agree to or accept as satisfactory. Allow : let (someone) have or do something. Break : separate into pieces as a result of a blow, shock, or strain. Abolish : formally put an end to (a system, practice, or institution). Cancel : neutralize or negate the force or effect of . Synonym of Cancel is Abolish."
    },
    {
        "question": "ABANDON :",
        "options": [
            {
                "option": "A.",
                "text": "Forsake"
            },
            {
                "option": "B.",
                "text": "Keep"
            },
            {
                "option": "C.",
                "text": "Cherish"
            },
            {
                "option": "D.",
                "text": "Enlarge"
            }
        ],
        "answer": "Option A",
        "solution": "Answer & Solution Answer: Option A Solution: Keep : have or retain possession of. Cherish : protect and care for (someone) lovingly. Enlarge : make or become larger or more extensive. Forsake : abandon or leave. Abandon : cease to support or look after (someone), desert. Synonym of Abandon is Forsake."
    },
    {
        "question": "GERMINATE :",
        "options": [
            {
                "option": "A.",
                "text": "Decay"
            },
            {
                "option": "B.",
                "text": "Breed"
            },
            {
                "option": "C.",
                "text": "Produce"
            },
            {
                "option": "D.",
                "text": "Sprout"
            }
        ],
        "answer": "Option D",
        "solution": "Answer & Solution Answer: Option D Solution: Decay : rot or decompose through the action of bacteria and fungi. Produce : make or manufacture from components or raw materials. Sprout : put out shoots. Breed : mate and then produce offspring. Germinate : begin to grow and put out shoots after a period of dormancy. Synonym of Germinate is Sprout ."
    },
    {
        "question": "RECUPERATE :",
        "options": [
            {
                "option": "A.",
                "text": "Rehabilitate"
            },
            {
                "option": "B.",
                "text": "Recover"
            },
            {
                "option": "C.",
                "text": "Reimburse"
            },
            {
                "option": "D.",
                "text": "Relocate"
            }
        ],
        "answer": "Option B",
        "solution": "Answer & Solution Answer: Option B Solution: Rehabilitate : restore (someone) to health or normal life by training and therapy after imprisonment, addiction, or illness. Reimburse : repay (a person who has spent or lost money). Relocate : move to a new place and establish one's home or business there. Recover : return to a normal state of health, mind, or strength. Recuperate : recover or regain (something lost or taken). Synonym of Recuperate is Recover."
    },
    {
        "question": "AUGURY:",
        "options": [
            {
                "option": "A.",
                "text": "Prophecy"
            },
            {
                "option": "B.",
                "text": "Astronomy"
            },
            {
                "option": "C.",
                "text": "Intention"
            },
            {
                "option": "D.",
                "text": "Future"
            }
        ],
        "answer": "Option A",
        "solution": "Answer & Solution Answer: Option A Solution: Prophecy : a prediction of what will happen in the future. Intention : a thing intended, an aim or plan. Astronomy : the branch of science which deals with celestial objects, space, and the physical universe as a whole. Future : a period of time following the moment of speaking or writing, time regarded as still to come. Augury : a sign of what will happen in the future, an omen. Synonym of Augury is Prophecy."
    },
    {
        "question": "DELECTABLE:",
        "options": [
            {
                "option": "A.",
                "text": "Nobel"
            },
            {
                "option": "B.",
                "text": "Enjoyable"
            },
            {
                "option": "C.",
                "text": "Delicious"
            },
            {
                "option": "D.",
                "text": "Sumptuous"
            }
        ],
        "answer": "Option C",
        "solution": "Answer & Solution Answer: Option C Solution: Nobel : belonging to a hereditary class with high social or political status, aristocratic. Enjoyable : giving delight or pleasure. Delicious : tasty, yummy, palatable, nice, toothsome. Sumptuous : splendid and expensive-looking. Delectable : (of food or drink) delicious. Synonym of Delectable is Delicious."
    },
    {
        "question": "DIELECTRIC :",
        "options": [
            {
                "option": "A.",
                "text": "Nonconductor"
            },
            {
                "option": "B.",
                "text": "Instructive"
            },
            {
                "option": "C.",
                "text": "Constructive"
            },
            {
                "option": "D.",
                "text": "Destructive"
            }
        ],
        "answer": "Option A",
        "solution": "Answer & Solution Answer: Option A Solution: Instructive : useful and informative. Constructive : serving a useful purpose; tending to build up. Destructive : causing great and irreparable harm or damage. Nonconductor : dielectric, insulator Dielectric : having the property of transmitting electric force without conduction; insulating. Synonym of Dielectric is Nonconductor."
    },
    {
        "question": "PALTRY :",
        "options": [
            {
                "option": "A.",
                "text": "Insignificant"
            },
            {
                "option": "B.",
                "text": "Unfair"
            },
            {
                "option": "C.",
                "text": "Average"
            },
            {
                "option": "D.",
                "text": "Slovenly"
            }
        ],
        "answer": "Option A",
        "solution": "Answer & Solution Answer: Option A Solution: Unfair :not based on or behaving according to the principles of equality and justice. Average :medium, moderate, intermediate, passable, dim. Slovenly :(especially of a person or their appearance) messy and dirty. Insignificant :too small or unimportant to be worth consideration. Paltry :(of an amount) small or meager. Synonym of Paltry is Insignificant."
    },
    {
        "question": "DISPARAGE :",
        "options": [
            {
                "option": "A.",
                "text": "Scatter"
            },
            {
                "option": "B.",
                "text": "Discriminate"
            },
            {
                "option": "C.",
                "text": "Belittle"
            },
            {
                "option": "D.",
                "text": "Waste"
            },
            {
                "option": "E.",
                "text": "Parable"
            }
        ],
        "answer": "Option C",
        "solution": "Answer & Solution Answer: Option C Solution: To scatter :throw in various random directions. Discriminate :recognize a distinction, differentiate. Waste : use or expend carelessly, extravagantly, or to no purpose. Parable :a simple story used to illustrate a moral or spiritual lesson, as told by Jesus in the Gospels. Belittle :make (someone or something) seem unimportant. Disparage :regard or represent as being of little worth. Synonym of Disparage is Belittle."
    },
    {
        "question": "ALACRITY :",
        "options": [
            {
                "option": "A.",
                "text": "Briskness"
            },
            {
                "option": "B.",
                "text": "Fear"
            },
            {
                "option": "C.",
                "text": "Frankness"
            },
            {
                "option": "D.",
                "text": "Alarm"
            },
            {
                "option": "E.",
                "text": "None of these"
            }
        ],
        "answer": "Option A",
        "solution": "Answer & Solution Answer: Option A Solution: Fear :an unpleasant emotion caused by the belief that someone or something is dangerous, likely to cause pain, or a threat. Frankness :open, honest, and direct in speech or writing, especially when dealing with unpalatable matters. Alarm :an anxious awareness of danger, warning, alert, caveat, caution, admonition. Briskness :active, fast, and energetic. Alacrity :brisk and cheerful readiness. Synonym of Alacrity is Briskness."
    },
    {
        "question": "BUSY :",
        "options": [
            {
                "option": "A.",
                "text": "Active"
            },
            {
                "option": "B.",
                "text": "Occupied"
            },
            {
                "option": "C.",
                "text": "Preoccupied"
            },
            {
                "option": "D.",
                "text": "Diligent"
            },
            {
                "option": "E.",
                "text": "None of these"
            }
        ],
        "answer": "Option B",
        "solution": "Answer & Solution Answer: Option B Solution: Active :(of a person) engaging or ready to engage in physically energetic pursuits. Preoccupied : restless, nervous, fidgety, feverish, disquieting, preoccupied. Diligent :having or showing care and conscientiousness in one's work or duties. Occupied :busy and active Busy > engaged, dissipated, active, disperse. Synonym of Busy is Occupied."
    },
    {
        "question": "BITTERNESS :",
        "options": [
            {
                "option": "A.",
                "text": "Sourness"
            },
            {
                "option": "B.",
                "text": "Hoarseness"
            },
            {
                "option": "C.",
                "text": "Acrimony"
            },
            {
                "option": "D.",
                "text": "Aspersion"
            },
            {
                "option": "E.",
                "text": "None of these"
            }
        ],
        "answer": "Option C",
        "solution": "Answer & Solution Answer: Option C Solution: Sourness :having an acid taste like lemon or vinegar. Hoarseness :sounding rough and harsh, typically as the result of a sore throat or of shouting. Aspersion :an attack on the reputation or integrity of someone or something. Acrimony :bitterness or ill feeling. Bitterness :sharpness of taste, lack of sweetness. Synonym of Bitterness is Acrimony."
    },
    {
        "question": "STERILE :",
        "options": [
            {
                "option": "A.",
                "text": "Dry"
            },
            {
                "option": "B.",
                "text": "Barren"
            },
            {
                "option": "C.",
                "text": "Childless"
            },
            {
                "option": "D.",
                "text": "None of these"
            }
        ],
        "answer": "Option B",
        "solution": "Answer & Solution Answer: Option B Solution: Dry :free from moisture or liquid, not wet or moist. Childless :issueless. Barren :too poor to produce much or any vegetation or any child. Sterile :not able to produce children or young. Synonym of Sterile is Barren."
    },
    {
        "question": "ALTERCATION :",
        "options": [
            {
                "option": "A.",
                "text": "Choice"
            },
            {
                "option": "B.",
                "text": "Charge"
            },
            {
                "option": "C.",
                "text": "Heated dispute"
            },
            {
                "option": "D.",
                "text": "Distribution"
            },
            {
                "option": "E.",
                "text": "None of these"
            }
        ],
        "answer": "Option C",
        "solution": "Answer & Solution Answer: Option C Solution: Choice :an act of selecting or making a decision when faced with two or more possibilities. Charge :demand (an amount) as a price from someone for a service rendered or goods supplied. Distribution :the action of sharing something out among a number of recipients. Heated dispute :wrangling, altercation, squabble, contention, controversy. Altercation :a noisy argument or disagreement, especially in public. Synonym of Altercation is Heated dispute."
    },
    {
        "question": "PROHIBIT :",
        "options": [
            {
                "option": "A.",
                "text": "Prescribe"
            },
            {
                "option": "B.",
                "text": "Forfeit"
            },
            {
                "option": "C.",
                "text": "Forbid"
            },
            {
                "option": "D.",
                "text": "Provide"
            }
        ],
        "answer": "Option C",
        "solution": "Answer & Solution Answer: Option C Solution: Prescribe :advise and authorize the use of (a medicine or treatment) for someone, especially in writing. Forfeit :lose or be deprived of (property or a right or privilege) as a penalty for wrongdoing. Provide :make available for use, supply. Forbid :refuse to allow (something). Prohibit :formally forbid (something) by law, rule, or other authority. Synonym of Prohibit is Forbid."
    },
    {
        "question": "STUPID :",
        "options": [
            {
                "option": "A.",
                "text": "Rude"
            },
            {
                "option": "B.",
                "text": "Dull"
            },
            {
                "option": "C.",
                "text": "Illiterate"
            },
            {
                "option": "D.",
                "text": "Obstinate"
            }
        ],
        "answer": "Option B",
        "solution": "Answer & Solution Answer: Option B Solution: Rude :offensively impolite or ill-mannered. Illiterate :unable to read or write. Obstinate :stubbornly refusing to change one's opinion or chosen course of action, despite attempts to persuade one to do so. Dull :slow to understand; stupid. Stupid :lacking intelligence or common sense. Synonym of Stupid is Dull."
    },
    {
        "question": "Synopsis :",
        "options": [
            {
                "option": "A.",
                "text": "Index"
            },
            {
                "option": "B.",
                "text": "Mixture"
            },
            {
                "option": "C.",
                "text": "Summary"
            },
            {
                "option": "D.",
                "text": "Puzzle"
            }
        ],
        "answer": "Option C",
        "solution": "Answer & Solution Answer: Option C Solution: Index :an indicator, sign, or measure of something. Mixture :a substance made by mixing other substances together. Puzzle :cause (someone) to feel confused because they cannot understand or make sense of something. Summary :a brief statement or account of the main points of something. Synopsis :a brief summary or general survey of something. Synonym of Synopsis is Summary."
    },
    {
        "question": "GRAPHIC :",
        "options": [
            {
                "option": "A.",
                "text": "Moving"
            },
            {
                "option": "B.",
                "text": "Timid"
            },
            {
                "option": "C.",
                "text": "Obvious"
            },
            {
                "option": "D.",
                "text": "Instructive"
            }
        ],
        "answer": "Option C",
        "solution": "Answer & Solution Answer: Option C Solution: Moving :in motion. Timid : showing a lack of courage or confidence; easily frightened. Instructiveuseful and informative. Obvious :easily perceived or understood; clear, self-evident, or apparent. Graphic :clear, apparent, pronounced, straightforward, glaring, graphic. Synonym of Graphic is Obvious."
    },
    {
        "question": "SHOWY :",
        "options": [
            {
                "option": "A.",
                "text": "Rowdy"
            },
            {
                "option": "B.",
                "text": "Hungry"
            },
            {
                "option": "C.",
                "text": "Greedy"
            },
            {
                "option": "D.",
                "text": "Gaudy"
            }
        ],
        "answer": "Option D",
        "solution": "Answer & Solution Answer: Option D Solution: Rowdy :noisy and disorderly. Hungry :feeling or displaying the need for food. Greedy :having or showing an intense and selfish desire for something, especially wealth or power. Gaudy :extravagantly bright or showy, typically so as to be tasteless Showy :having a striking appearance or style, typically by being excessively bright, colorful, or ostentatious. Synonym of Showy is Gaudy."
    },
    {
        "question": "ANNIHILATE :",
        "options": [
            {
                "option": "A.",
                "text": "Destroy"
            },
            {
                "option": "B.",
                "text": "Entrain"
            },
            {
                "option": "C.",
                "text": "Forward"
            },
            {
                "option": "D.",
                "text": "testify"
            }
        ],
        "answer": "Option A",
        "solution": "Answer & Solution Answer: Option A Solution: Entrain :climb, ascend, climb up, entrain, board, mount. Forward :toward the front; in the direction that one is facing or traveling. Testify :give evidence as a witness in a law court. Destroy :put an end to the existence of (something) by damaging or attacking it. Annihilate :destroy utterly obliterate. Synonym of Annihilate is Destroy."
    },
    {
        "question": "PACIFY :",
        "options": [
            {
                "option": "A.",
                "text": "Gather"
            },
            {
                "option": "B.",
                "text": "Allot"
            },
            {
                "option": "C.",
                "text": "Calm"
            },
            {
                "option": "D.",
                "text": "Remit"
            }
        ],
        "answer": "Option C",
        "solution": "Answer & Solution Answer: Option C Solution: Gather :come together; assemble or accumulate. Allot :give or apportion (something) to someone as a share or task. Remit :cancel or refrain from exacting or inflicting (a debt or punishment). Calm :not showing or feeling nervousness, anger, or other emotions. Pacify : calm. Synonym of Pacify is Calm."
    },
    {
        "question": "LIBERAL :",
        "options": [
            {
                "option": "A.",
                "text": "Broad-minded"
            },
            {
                "option": "B.",
                "text": "Generous"
            },
            {
                "option": "C.",
                "text": "Visionary"
            },
            {
                "option": "D.",
                "text": "Imaginative"
            }
        ],
        "answer": "Option A",
        "solution": "Answer & Solution Answer: Option A Solution: Let's look at each option: Option A: Broad-minded means having or showing an open, tolerant attitude. Option B: Generous means showing a readiness to give more of something, especially money, than is strictly necessary or expected. Option C: Visionary means thinking about or planning the future with imagination or wisdom. Option D: Imaginative means having or showing a tendency to form new, often unconventional ideas. Think about the word \"liberal.\" It often describes someone who is open to new ideas and willing to accept different viewpoints. This matches the meaning of \"broad-minded.\" While \"generous\" can sometimes relate to a liberal person (like being liberal with their money), it's not the *primary* synonym. \"Visionary\" and \"imaginative\" are related to creativity but not directly to the core meaning of \"liberal.\" Therefore, the best synonym for \"LIBERAL\" is \"broad-minded.\""
    },
    {
        "question": "SECURITY :",
        "options": [
            {
                "option": "A.",
                "text": "Boldness"
            },
            {
                "option": "B.",
                "text": "Safety"
            },
            {
                "option": "C.",
                "text": "Fearlessness"
            },
            {
                "option": "D.",
                "text": "Confidence"
            }
        ],
        "answer": "Option B",
        "solution": "Answer & Solution Answer: Option B Solution: Boldness :showing a willingness to take risks, confident and courageous. Fearlessness :showing a lack of fear. Confidence :the feeling or belief that one can have faith in or rely on someone or something. Safety :the condition of being protected from or unlikely to cause danger, risk, or injury. Security : the state of being free from danger or threat. Synonym of Security is Safety."
    },
    {
        "question": "DILIGENT :",
        "options": [
            {
                "option": "A.",
                "text": "Fool"
            },
            {
                "option": "B.",
                "text": "Unhappy"
            },
            {
                "option": "C.",
                "text": "Hardworking"
            },
            {
                "option": "D.",
                "text": "Disappointment"
            }
        ],
        "answer": "Option C",
        "solution": "Answer & Solution Answer: Option C Solution: Fool :a person who acts unwisely or imprudently, a silly person. Unhappy :not happy. Disappointment :sadness or displeasure caused by the non-fulfillment of one's hopes or expectations. Hardworking :tending to work with energy and commitment, diligent. Diligent :having or showing care and conscientiousness in one's work or duties. Synonym of Diligent is Hardworking."
    },
    {
        "question": "PREDOMINANT :",
        "options": [
            {
                "option": "A.",
                "text": "Lovable"
            },
            {
                "option": "B.",
                "text": "Important"
            },
            {
                "option": "C.",
                "text": "Vague"
            },
            {
                "option": "D.",
                "text": "Assurance"
            }
        ],
        "answer": "Option B",
        "solution": "Answer & Solution Answer: Option B Solution: Lovable :inspiring or deserving love or affection. Vague :of uncertain, indefinite, or unclear character or meaning. Assurance :a positive declaration intended to give confidence, a promise. Important :of great significance or value. Predominant :present as the strongest or main element, important Synonym of Predominant is Important."
    },
    {
        "question": "UTILITY :",
        "options": [
            {
                "option": "A.",
                "text": "Benefit"
            },
            {
                "option": "B.",
                "text": "Usefulness"
            },
            {
                "option": "C.",
                "text": "Profitability"
            },
            {
                "option": "D.",
                "text": "Advantage"
            }
        ],
        "answer": "Option B",
        "solution": "Answer & Solution Answer: Option B Solution: Benefit :an advantage or profit gained from something. Profitability : yielding profit or financial gain. Advantage :a condition or circumstance that puts one in a favourable or superior position. Usefulness :the quality or fact of being useful. Utility :the state of being useful. Synonym of Utility is Usefulness."
    },
    {
        "question": "COMPASSION :",
        "options": [
            {
                "option": "A.",
                "text": "Kindness"
            },
            {
                "option": "B.",
                "text": "Similarity"
            },
            {
                "option": "C.",
                "text": "Contrast"
            },
            {
                "option": "D.",
                "text": "Cruelty"
            }
        ],
        "answer": "Option A",
        "solution": "Answer & Solution Answer: Option A Solution: Similarity : the state or fact of being similar. Contrast :abnormality, oddity, dissimilarity, disproportion, irregularity. Cruelty :cruel behaviour or attitudes. Kindness :the quality of being friendly, generous, and considerate. Compassion :sympathetic pity and concern for the sufferings or misfortunes of others. Synonym of Compassion is Kindness."
    },
    {
        "question": "CONTENTMENT :",
        "options": [
            {
                "option": "A.",
                "text": "Craftiness"
            },
            {
                "option": "B.",
                "text": "Satisfaction"
            },
            {
                "option": "C.",
                "text": "Idleness"
            },
            {
                "option": "D.",
                "text": "Craving"
            }
        ],
        "answer": "Option B",
        "solution": "Answer & Solution Answer: Option B Solution: Craftiness :clever at achieving one's aims by indirect or deceitful methods. Idleness :laziness, indolence. Craving :a powerful desire for something. Satisfaction :fulfillment of one's wishes, expectations, or needs, or the pleasure derived from this. Contentment :a state of happiness and satisfaction. Synonym of Contentment is Satisfaction."
    },
    {
        "question": "FICTION :",
        "options": [
            {
                "option": "A.",
                "text": "Imaginary"
            },
            {
                "option": "B.",
                "text": "Tamed"
            },
            {
                "option": "C.",
                "text": "Novel"
            },
            {
                "option": "D.",
                "text": "Wildness"
            }
        ],
        "answer": "Option A",
        "solution": "Answer & Solution Answer: Option A Solution: Imaginary :existing only in the imagination. Tamed :not dangerous or frightened of people, domesticated Wildness :lacking discipline or restraint. Novel :a fictitious prose narrative of book length, typically representing character and action with some degree of realism. Fiction : literature in the form of prose, especially novels, that describes imaginary events and people. Synonym of Fiction is Novel."
    },
    {
        "question": "FUGITIVE :",
        "options": [
            {
                "option": "A.",
                "text": "Escaping"
            },
            {
                "option": "B.",
                "text": "Enduring"
            },
            {
                "option": "C.",
                "text": "Vain"
            },
            {
                "option": "D.",
                "text": "Weak"
            }
        ],
        "answer": "Option A",
        "solution": "Answer & Solution Answer: Option A Solution: Enduring :lasting over a period of time, durable. Vain :producing no result, useless. Weak :lacking the power to perform physically demanding tasks, having little physical strength or energy. Escaping :break free from confinement or control. Fugitive :a person who has escaped from captivity or is in hiding. Synonym of Fugitive is Escaping."
    },
    {
        "question": "EXPONENT :",
        "options": [
            {
                "option": "A.",
                "text": "Meddler"
            },
            {
                "option": "B.",
                "text": "Cancel"
            },
            {
                "option": "C.",
                "text": "Advocate"
            },
            {
                "option": "D.",
                "text": "Horrid"
            }
        ],
        "answer": "Option C",
        "solution": "Answer & Solution Answer: Option C Solution: Meddler : one who interfere in something that is not one's concern. Cancel :decide or announce that (a planned event) will not take place. Horrid :causing horror. Advocate :a person who publicly supports or recommends a particular cause or policy. Exponent :a person who supports an idea or theory and tries to persuade people of its truth or benefits. Synonym of Exponent is Advocate."
    },
    {
        "question": "GOAD :",
        "options": [
            {
                "option": "A.",
                "text": "Soothe"
            },
            {
                "option": "B.",
                "text": "Save"
            },
            {
                "option": "C.",
                "text": "Irritate"
            },
            {
                "option": "D.",
                "text": "Worship"
            }
        ],
        "answer": "Option C",
        "solution": "Answer & Solution Answer: Option C Solution: Soothe :gently calm. Save :keep and store up for future use. Worship :the feeling or expression of reverence and adoration for a deity. Irritate :make (someone) annoyed or a little angry. Goad :provoke or annoy (someone) so as to stimulate an action or reaction. Synonym of Goad is Irritate."
    },
    {
        "question": "FOMENT :",
        "options": [
            {
                "option": "A.",
                "text": "Extirpate"
            },
            {
                "option": "B.",
                "text": "Provoke"
            },
            {
                "option": "C.",
                "text": "Isolation"
            },
            {
                "option": "D.",
                "text": "Abrasion"
            }
        ],
        "answer": "Option B",
        "solution": "Answer & Solution Answer: Option B Solution: Extirpate :eradicate or destroy completely. Isolation :the process or fact of isolating or being isolated. Abrasion :the process of scraping or wearing something away. Provoke :stimulate or give rise to (a reaction or emotion, typically a strong or unwelcome one) in someone. Foment : instigate or stir up . Synonym of Foment is Provoke."
    },
    {
        "question": "IMPERCEPTIBLE :",
        "options": [
            {
                "option": "A.",
                "text": "Mean"
            },
            {
                "option": "B.",
                "text": "Obvious"
            },
            {
                "option": "C.",
                "text": "Humble"
            },
            {
                "option": "D.",
                "text": "Subtle"
            }
        ],
        "answer": "Option D",
        "solution": "Answer & Solution Answer: Option D Solution: Imperceptible-so slight ,gradual,or subtle as not to be perceived Mean-signify, intend to convey or refer Obvious-easily perceived or understood Humble-having r showing a modest or low estimate of one's importance Subtle-so delicate or precise as to b difficult to analyse or describe So, synonym of Imperceptible is Subtle."
    },
    {
        "question": "SEE :",
        "options": [
            {
                "option": "A.",
                "text": "Talk"
            },
            {
                "option": "B.",
                "text": "Observe"
            },
            {
                "option": "C.",
                "text": "Stand"
            },
            {
                "option": "D.",
                "text": "Look"
            }
        ],
        "answer": "Option B",
        "solution": "Answer & Solution Answer: Option B Solution: Talk :speak in order to give information or express ideas or feelings, converse or communicate by spoken words. Stand : have or maintain an upright position, supported by one's feet. Look :direct one's gaze in a specified direction. Observe :notice or perceive (something) and register it as being significant. See :perceive with the eyes, discern visually. Synonym of See is Observe."
    },
    {
        "question": "INSTALLED :",
        "options": [
            {
                "option": "A.",
                "text": "Prepared"
            },
            {
                "option": "B.",
                "text": "Settled"
            },
            {
                "option": "C.",
                "text": "Started"
            },
            {
                "option": "D.",
                "text": "Manufactured"
            },
            {
                "option": "E.",
                "text": "Established"
            }
        ],
        "answer": "Option E",
        "solution": "Answer & Solution Answer: Option E Solution: Prepared :make (something) ready for use or consideration. Settled :resolve or reach an agreement about. Started :begin or be reckoned from a particular point in time or space, come into being. Manufactured :Manufactured. Established :having existed or done something for a long time and therefore recognized and generally accepted. Installed :place or fix (equipment or machinery) in position ready for use. Synonym of Installed is Established."
    },
    {
        "question": "CONTAIN :",
        "options": [
            {
                "option": "A.",
                "text": "Prevent"
            },
            {
                "option": "B.",
                "text": "Limit"
            },
            {
                "option": "C.",
                "text": "Hold"
            },
            {
                "option": "D.",
                "text": "Express"
            },
            {
                "option": "E.",
                "text": "Control"
            }
        ],
        "answer": "Option C",
        "solution": "Answer & Solution Answer: Option C Solution: Prevent :keep (something) from happening. Limita point or level beyond which something does not or may not extend or pass. Express :convey (a thought or feeling) in words or by gestures and conduct. Control :the power to influence or direct people's behaviour or the course of events. Hold :grasp, carry, or support with one's arms or hands. Contain :have or hold (someone or something) within. Synonym of Contain is Hold"
    },
    {
        "question": "EVENTUALLY :",
        "options": [
            {
                "option": "A.",
                "text": "Suddenly"
            },
            {
                "option": "B.",
                "text": "Ultimately"
            },
            {
                "option": "C.",
                "text": "Quickly"
            },
            {
                "option": "D.",
                "text": "Abruptly"
            },
            {
                "option": "E.",
                "text": "Initially"
            }
        ],
        "answer": "Option B",
        "solution": "Answer & Solution Answer: Option B Solution: Suddenly :quickly and unexpectedly. Quickly :at a fast speed, rapidly. Abruptly :sudden and unexpected. Initially :at first. Ultimately :finally, in the end. Eventually :in the end, especially after a long delay, dispute, or series of problems. Synonym of Eventually is Ultimately."
    },
    {
        "question": "ESSENTIAL :",
        "options": [
            {
                "option": "A.",
                "text": "Desirable"
            },
            {
                "option": "B.",
                "text": "Advisable"
            },
            {
                "option": "C.",
                "text": "Beneficial"
            },
            {
                "option": "D.",
                "text": "Unavoidable"
            }
        ],
        "answer": "Option D",
        "solution": "Answer & Solution Answer: Option D Solution: Desirable :catchy, glamorous, pleasing, fetching, likable. Advisable : to be recommended. Beneficialresulting in good; favourable or advantageous. Unavoidable :not able to be avoided, prevented, or ignored; inevitable. Essential :absolutely necessary; extremely important. Synonym of Essential is Unavoidable."
    },
    {
        "question": "TURN :",
        "options": [
            {
                "option": "A.",
                "text": "Shift"
            },
            {
                "option": "B.",
                "text": "Curve"
            },
            {
                "option": "C.",
                "text": "Move"
            },
            {
                "option": "D.",
                "text": "Rotate"
            },
            {
                "option": "E.",
                "text": "Fabricate"
            }
        ],
        "answer": "Option D",
        "solution": "Answer & Solution Answer: Option D Solution: Curve : a line or outline which gradually deviates from being straight for some or all of its length. Move : go in a specified direction or manner; change position. Fabricate :concoct, mold, feign, excogitate, manufacture. Shift :move or cause to move from one place to another, especially over a small distance. Rotate :move or cause to move in a circle round an axis or centre. Turn :move or cause to move in a circular direction wholly or partly around an axis or point. Synonym of Turn is Rotate."
    },
    {
        "question": "AWAKENED :",
        "options": [
            {
                "option": "A.",
                "text": "Enlightened"
            },
            {
                "option": "B.",
                "text": "Realized"
            },
            {
                "option": "C.",
                "text": "Shook"
            },
            {
                "option": "D.",
                "text": "Briefed"
            }
        ],
        "answer": "Option A",
        "solution": "Answer & Solution Answer: Option A Solution: Realized :become fully aware of (something) as a fact; understand clearly. Shook : emotionally or physically disturbed, upset Briefed :concise, abbreviated, succinct, summary, terse. Enlightened :having or showing a rational, modern, and well-informed outlook, Awakened. Awakened :rouse from sleep; cause to stop sleeping. Synonym of Awakened is Enlightened."
    },
    {
        "question": "Diversion :",
        "options": [
            {
                "option": "A.",
                "text": "Amusement"
            },
            {
                "option": "B.",
                "text": "Distortion"
            },
            {
                "option": "C.",
                "text": "Deviation"
            },
            {
                "option": "D.",
                "text": "Change"
            }
        ],
        "answer": "Option C",
        "solution": "Answer & Solution Answer: Option C Solution: Distortion: the action of giving a misleading account or impression. Deviation: the action of departing from an established course or accepted standard. Change: make or become different. Amusement: the state or experience of finding something funny. Diversion: an activity that diverts the mind from tedious or serious concerns; a recreation or pastime. Synonym of Diversion is Distortion."
    },
    {
        "question": "PASS :",
        "options": [
            {
                "option": "A.",
                "text": "Qualify"
            },
            {
                "option": "B.",
                "text": "Die"
            },
            {
                "option": "C.",
                "text": "Cross"
            },
            {
                "option": "D.",
                "text": "Elongated"
            }
        ],
        "answer": "Option C",
        "solution": "Answer & Solution Answer: Option C Solution: Qualify : be entitled to a particular benefit or privilege by fulfilling a necessary condition. Die : stop living. Elongated :make (something) longer, especially unusually so in relation to its width. Cross :pass, pass over, traverse, vert, pass by. Pass : go past or across, leave behind or on one side in proceeding. Synonym of Pass is Cross."
    },
    {
        "question": "WRETCHED:",
        "options": [
            {
                "option": "A.",
                "text": "Poor"
            },
            {
                "option": "B.",
                "text": "Foolish"
            },
            {
                "option": "C.",
                "text": "Insane"
            },
            {
                "option": "D.",
                "text": "Strained"
            },
            {
                "option": "E.",
                "text": "Transfer"
            }
        ],
        "answer": "Option A",
        "solution": "Answer & Solution Answer: Option A Solution: Foolish :lacking good sense or judgement, unwise. Insane :in a state of mind which prevents normal perception, behaviour, or social interaction; seriously mentally ill. Strained :showing signs of nervous tension or tiredness. Transfer :move from one place to another. Poor : lacking sufficient money to live at a standard considered comfortable or normal in a society. Wretched : in a very unhappy or unfortunate state. Synonym of Wretched is Poor."
    },
    {
        "question": "DUPLICITY :",
        "options": [
            {
                "option": "A.",
                "text": "Repetition"
            },
            {
                "option": "B.",
                "text": "Artlessness"
            },
            {
                "option": "C.",
                "text": "Deceit"
            },
            {
                "option": "D.",
                "text": "Cleverness"
            }
        ],
        "answer": "Option C",
        "solution": "Answer & Solution Answer: Option C Solution: Repetition:the action of repeating something that has already been said or written. Artlessness :talentless. Cleverness :the quality of being clever; intelligence or shrewdness. Deceit :the action or practice of deceiving someone by concealing or misrepresenting the truth. Duplicity :deceitfulness. Synonym of Duplicity is Deceit."
    },
    {
        "question": "VANGUARD :",
        "options": [
            {
                "option": "A.",
                "text": "Race driver"
            },
            {
                "option": "B.",
                "text": "Officer"
            },
            {
                "option": "C.",
                "text": "Flag bearer"
            },
            {
                "option": "D.",
                "text": "Pioneer"
            }
        ],
        "answer": "Option D",
        "solution": "Answer & Solution Answer: Option D Solution: Race driver : someone who drives racing cars at high speeds. Officer : a person holding a position of authority, especially one with a commission, in the armed services, the mercantile marine, or on a passenger ship. Flag bearer : One who carries a flag, especially at a ceremony. Pioneer : a person who is among the first to research and develop a new area of knowledge or activity. Vanguard : a group of people leading the way in new developments or ideas. Synonym of Vanguard is Flag bearer"
    },
    {
        "question": "FORTITUDE :",
        "options": [
            {
                "option": "A.",
                "text": "Similarity"
            },
            {
                "option": "B.",
                "text": "Courage"
            },
            {
                "option": "C.",
                "text": "Protection"
            },
            {
                "option": "D.",
                "text": "Safety"
            }
        ],
        "answer": "Option B",
        "solution": "Answer & Solution Answer: Option B Solution: Synonym of FORTITUDE is Courage. Word Meaning \/ Definition Use of the words Similarity a similar feature or aspect. The similarities between people of different nationalities. Protection the action of protecting, or the state of being protected. The B vitamins give protection against infection. Safety The condition of being protected from or unlikely to cause danger, risk, or injury The survivors were airlifted to safety. Courage The ability to do something that frightens one; bravery. She called on all her courage to face the ordeal. FORTITUDE Courage in pain or adversity. She endured her illness with great fortitude."
    },
    {
        "question": "INADVERTENT :",
        "options": [
            {
                "option": "A.",
                "text": "Ignorant"
            },
            {
                "option": "B.",
                "text": "Unexpected"
            },
            {
                "option": "C.",
                "text": "Unintentional"
            },
            {
                "option": "D.",
                "text": "Undisturbed"
            }
        ],
        "answer": "Option C",
        "solution": "Answer & Solution Answer: Option C Solution: Ignorant : lacking knowledge or awareness in general; uneducated or unsophisticated. Unexpected : not expected or regarded as likely to happen. Unintentional : not done on purpose. Undisturbed : not disturbed. Inadvertent : not resulting from or achieved through deliberate planning. Synonym of Inadvertent is Unintentional"
    },
    {
        "question": "FIDELITY :",
        "options": [
            {
                "option": "A.",
                "text": "Faithfulness"
            },
            {
                "option": "B.",
                "text": "Resourcefulness"
            },
            {
                "option": "C.",
                "text": "Strength"
            },
            {
                "option": "D.",
                "text": "Weakness"
            }
        ],
        "answer": "Option A",
        "solution": "Answer & Solution Answer: Option A Solution: Faithfulness : the quality of being faithful; fidelity. Resourcefulness : the ability to find quick and clever ways to overcome difficulties. Strength : the quality or state of being physically strong. Weakness : the state or condition of being weak. Fidelity : faithfulness to a person, cause, or belief, demonstrated by continuing loyalty and support. Synonym of Fidelity is Faithfulness"
    },
    {
        "question": "CATER :",
        "options": [
            {
                "option": "A.",
                "text": "Advance"
            },
            {
                "option": "B.",
                "text": "Develop"
            },
            {
                "option": "C.",
                "text": "Provide"
            },
            {
                "option": "D.",
                "text": "Discover"
            }
        ],
        "answer": "Option C",
        "solution": "Answer & Solution Answer: Option C Solution: Advance :move forwards in a purposeful way. Develop : grow or cause to grow and become more mature, advanced, or elaborate. Discover: find unexpectedly. Provide : make available for use; supply. CATER : : provide with what is needed or required. Synonym of CATER is Provide."
    },
    {
        "question": "REDRESSED :",
        "options": [
            {
                "option": "A.",
                "text": "Addressed"
            },
            {
                "option": "B.",
                "text": "Equalised"
            },
            {
                "option": "C.",
                "text": "Restored"
            },
            {
                "option": "D.",
                "text": "Redone"
            },
            {
                "option": "E.",
                "text": "Rearranged"
            }
        ],
        "answer": "Option C",
        "solution": "Answer & Solution Answer: Option C Solution: Addressed : a formal speech delivered to an audience. Equalised : make the same in quantity, size, or degree throughout a place or group. Redone : do (something) again or differently. Rearranged : change (the position, time, or order of something). Restored : bring back or re-establish (a previous right, practice, or situation). REDRESSED : remedy or set right or bring back. Synonym of REDRESSED is Restored."
    },
    {
        "question": "HAGGLE:",
        "options": [
            {
                "option": "A.",
                "text": "Postpone"
            },
            {
                "option": "B.",
                "text": "Accept"
            },
            {
                "option": "C.",
                "text": "Bargain"
            },
            {
                "option": "D.",
                "text": "Reject"
            }
        ],
        "answer": "Option C",
        "solution": "Answer & Solution Answer: Option C Solution: Postpone :A cause or arrange for (something) to take place at a time later than that first scheduled. Accept :Consent to receive or undertake Reject :Dismiss, unacceptable, or faulty Bargain :Negotiate the terms and conditions of a transaction. HAGGLE: :Dispute or bargain persistently, especially over the cost of something. Synonym of HAGGLE is Bargain."
    },
    {
        "question": "ABSTRUSE:",
        "options": [
            {
                "option": "A.",
                "text": "Awful"
            },
            {
                "option": "B.",
                "text": "Irrelevant"
            },
            {
                "option": "C.",
                "text": "Shallow"
            },
            {
                "option": "D.",
                "text": "Profound"
            }
        ],
        "answer": "Option D",
        "solution": "Answer & Solution Answer: Option D Solution: ABSTRUSE means something that is hard to understand or obscure. Among the given options, the word Profound refers to something that is deep or complex in meaning, which closely aligns with the meaning of Abstruse. On the other hand: Awful means terrible or very bad – not related. Irrelevant means not related to the subject – unrelated in meaning. Shallow means lacking depth – actually the opposite of abstruse. Therefore, Profound is the most appropriate synonym for Abstruse."
    },
    {
        "question": "YOB:",
        "options": [
            {
                "option": "A.",
                "text": "Aggressive"
            },
            {
                "option": "B.",
                "text": "Intelligent"
            },
            {
                "option": "C.",
                "text": "Annoyed"
            },
            {
                "option": "D.",
                "text": "Humble"
            }
        ],
        "answer": "Option A",
        "solution": "Answer & Solution Answer: Option A Solution: Aggressive :ready or likely to attack or confront. Intelligent :having or showing intelligence. Annoyed :slightly angry; irritated. Humble :Having or showing a modest or low estimate of one's importance. YOB :a rude, noisy, and aggressive youth. Synonym of YOB is Aggressive."
    },
    {
        "question": "CORPULENT",
        "options": [
            {
                "option": "A.",
                "text": "Lean"
            },
            {
                "option": "B.",
                "text": "Gaunt"
            },
            {
                "option": "C.",
                "text": "Emaciated"
            },
            {
                "option": "D.",
                "text": "Obese"
            }
        ],
        "answer": "Option D",
        "solution": "Answer & Solution Answer: Option D Solution: Lean : be in or move into a sloping position. Gaunt : (of a person) lean and haggard, especially because of suffering, hunger, or age. Emaciated : abnormally thin or weak, especially because of illness or a lack of food. Obese : grossly fat or overweight. Corpulent : (of a person) fat. Synonym of Corpulent is Obese"
    },
    {
        "question": "BRIEF",
        "options": [
            {
                "option": "A.",
                "text": "Limited"
            },
            {
                "option": "B.",
                "text": "Small"
            },
            {
                "option": "C.",
                "text": "Little"
            },
            {
                "option": "D.",
                "text": "Short"
            }
        ],
        "answer": "Option D",
        "solution": "Answer & Solution Answer: Option D Solution: Limited : restricted in size, amount, or extent. Small : of a size that is less than normal or usual. Little : small in size, amount, or degree. Short : lasting or taking a small amount of time. Brief : of short duration; not lasting for long. Synonym of Brief is Short"
    },
    {
        "question": "EMBEZZLE",
        "options": [
            {
                "option": "A.",
                "text": "Misappropriate"
            },
            {
                "option": "B.",
                "text": "Balance"
            },
            {
                "option": "C.",
                "text": "Remunerate"
            },
            {
                "option": "D.",
                "text": "Clear"
            }
        ],
        "answer": "Option A",
        "solution": "Answer & Solution Answer: Option A Solution: Misappropriate : dishonestly or unfairly take (something, especially money, belonging to another) for one's own use. Balance : an even distribution of weight enabling someone or something to remain upright and steady. Remunerate : pay (someone) for services rendered or work done. Clear : easy to perceive, understand, or interpret. Embezzle : steal or misappropriate (money placed in one's trust or belonging to the organization for which one works). Synonym of Embezzle is Misappropriate"
    },
    {
        "question": "VENT",
        "options": [
            {
                "option": "A.",
                "text": "Opening"
            },
            {
                "option": "B.",
                "text": "Stodge"
            },
            {
                "option": "C.",
                "text": "End"
            },
            {
                "option": "D.",
                "text": "Past"
            }
        ],
        "answer": "Option A",
        "solution": "Answer & Solution Answer: Option A Solution: Opening : a space or gap that allows passage or access. Stodge : food that is heavy, filling, and high in carbohydrates. End : a final part of something, especially a period of time, an activity, or a story. Past : gone by in time and no longer existing. Vent : an opening that allows air, gas, or liquid to pass out of or into a confined space. Synonym of Vent is Opening"
    },
    {
        "question": "AUGUST",
        "options": [
            {
                "option": "A.",
                "text": "Common"
            },
            {
                "option": "B.",
                "text": "Ridiculous"
            },
            {
                "option": "C.",
                "text": "Dignified"
            },
            {
                "option": "D.",
                "text": "Petty"
            }
        ],
        "answer": "Option C",
        "solution": "Answer & Solution Answer: Option C Solution: Common : occurring, found, or done often; prevalent. Ridiculous : funny; hilarious. Dignified : having or showing a composed or serious manner that is worthy of respect. Petty : of little importance; trivial. August : respected and impressive. Synonym of August is Dignified"
    },
    {
        "question": "CANNY",
        "options": [
            {
                "option": "A.",
                "text": "Obstinate"
            },
            {
                "option": "B.",
                "text": "Handsome"
            },
            {
                "option": "C.",
                "text": "Clever"
            },
            {
                "option": "D.",
                "text": "Stout"
            }
        ],
        "answer": "Option C",
        "solution": "Answer & Solution Answer: Option C Solution: Obstinate : stubbornly refusing to change one's opinion or chosen course of action, despite attempts to persuade one to do so. Handsome : (of a man) good-looking. Clever : quick to understand, learn, and devise or apply ideas; intelligent. Stout : (of a person) rather fat or of heavy build. Canny : having or showing shrewdness and good judgement, especially in money or business matters. Synonym of Canny is Clever"
    },
    {
        "question": "ALERT",
        "options": [
            {
                "option": "A.",
                "text": "Energetic"
            },
            {
                "option": "B.",
                "text": "Observant"
            },
            {
                "option": "C.",
                "text": "Intelligent"
            },
            {
                "option": "D.",
                "text": "Watchful"
            }
        ],
        "answer": "Option D",
        "solution": "Answer & Solution Answer: Option D Solution: Energetic : showing or involving great activity or vitality. Observant : quick to notice or perceive things. Intelligent : having or showing intelligence, especially of a high level. Watchful : watching someone or something closely; alert and vigilant. Alert : quick to notice any unusual and potentially dangerous or difficult circumstances; vigilant. Synonym of Alert is Watchful"
    },
    {
        "question": "WARRIOR",
        "options": [
            {
                "option": "A.",
                "text": "Soldier"
            },
            {
                "option": "B.",
                "text": "Sailor"
            },
            {
                "option": "C.",
                "text": "Pirate"
            },
            {
                "option": "D.",
                "text": "Spy"
            }
        ],
        "answer": "Option A",
        "solution": "Answer & Solution Answer: Option A Solution: Soldier : a person who serves in an army. Sailor : a person whose job it is to work as a member of the crew of a commercial or naval ship or boat, especially one who is below the rank of officer. Pirate : a person who attacks and robs ships at sea. Spy : a person employed by a government or other organization to secretly obtain information on an enemy or competitor. Warrior : a brave or experienced soldier or fighter. Synonym of Warrior is Soldier"
    },
    {
        "question": "DISTANT",
        "options": [
            {
                "option": "A.",
                "text": "Far"
            },
            {
                "option": "B.",
                "text": "Removed"
            },
            {
                "option": "C.",
                "text": "Reserved"
            },
            {
                "option": "D.",
                "text": "Separate"
            }
        ],
        "answer": "Option A",
        "solution": "Answer & Solution Answer: Option A Solution: Far : at, to, or by a great distance. Removed : take (something) away or off from the position occupied. Reserved: slow to reveal emotion or opinions. Separate : forming or viewed as a unit apart or by itself. Distant : far away in space or time. Synonym of Distant is Far"
    },
    {
        "question": "ADVERSITY",
        "options": [
            {
                "option": "A.",
                "text": "Failure"
            },
            {
                "option": "B.",
                "text": "Helplessness"
            },
            {
                "option": "C.",
                "text": "Misfortune"
            },
            {
                "option": "D.",
                "text": "Crisis"
            }
        ],
        "answer": "Option C",
        "solution": "Answer & Solution Answer: Option C Solution: Failure : lack of success. Helplessness : inability to defend oneself or to act effectively. Misfortune : bad luck. Crisis : a time of intense difficulty or danger. Adversity : ill luck; bad luck. Synonym of Adversity is Misfortune"
    },
    {
        "question": "FAKE",
        "options": [
            {
                "option": "A.",
                "text": "Original"
            },
            {
                "option": "B.",
                "text": "Imitation"
            },
            {
                "option": "C.",
                "text": "Trustworthy"
            },
            {
                "option": "D.",
                "text": "Loyal"
            }
        ],
        "answer": "Option B",
        "solution": "Answer & Solution Answer: Option B Solution: Original : present or existing from the beginning. Imitation : the action of using someone or something as a model. Trustworthy : able to be relied on as honest or truthful. Loyal : giving or showing firm and constant support or allegiance to a person or institution. Fake : not genuine; imitation or counterfeit. Synonym of Fake is Imitation"
    },
    {
        "question": "INDICT",
        "options": [
            {
                "option": "A.",
                "text": "Condemn"
            },
            {
                "option": "B.",
                "text": "Reprimand"
            },
            {
                "option": "C.",
                "text": "Accuse"
            },
            {
                "option": "D.",
                "text": "Allege"
            }
        ],
        "answer": "Option C",
        "solution": "Answer & Solution Answer: Option C Solution: Condemn : express complete disapproval of. Reprimand : a formal expression of disapproval. Accuse : charge (someone) with an offence or crime. Allege : claim or assert that someone has done something illegal or wrong, typically without proof. Indict : formally accuse of or charge with a crime. Synonym of Indict is Accuse"
    },
    {
        "question": "STRINGENT",
        "options": [
            {
                "option": "A.",
                "text": "Dry"
            },
            {
                "option": "B.",
                "text": "Strained"
            },
            {
                "option": "C.",
                "text": "Rigorous"
            },
            {
                "option": "D.",
                "text": "Shrill"
            }
        ],
        "answer": "Option C",
        "solution": "Answer & Solution Answer: Option C Solution: Dry : free from moisture or liquid; not wet or moist. Strained : showing signs of nervous tension or tiredness. Rigorous : extremely thorough and careful. Shrill : (of a voice or sound) high-pitched and piercing. Stringent : exacting. Synonym of Stringent is Rigorous"
    },
    {
        "question": "LAMENT",
        "options": [
            {
                "option": "A.",
                "text": "Complain"
            },
            {
                "option": "B.",
                "text": "Comment"
            },
            {
                "option": "C.",
                "text": "Condone"
            },
            {
                "option": "D.",
                "text": "Console"
            }
        ],
        "answer": "Option A",
        "solution": "Answer & Solution Answer: Option A Solution: Complain : express dissatisfaction or annoyance about something. Comment : a verbal or written remark expressing an opinion or reaction. Condone : accept (behaviour that is considered morally wrong or offensive). Console : comfort (someone) at a time of grief or disappointment. Lament : a complaint. Synonym of Lament is Complain"
    },
    {
        "question": "HESITATED",
        "options": [
            {
                "option": "A.",
                "text": "Stopped"
            },
            {
                "option": "B.",
                "text": "Paused"
            },
            {
                "option": "C.",
                "text": "Slowed"
            },
            {
                "option": "D.",
                "text": "Postponed"
            }
        ],
        "answer": "Option B",
        "solution": "Answer & Solution Answer: Option B Solution: Stopped : (of an event, action, or process) come to an end. Paused : interrupt action or speech briefly. Slowed : reduce one's speed or the speed of a vehicle or process. Postponed : cause or arrange for (something) to take place at a time later than that first scheduled. Hesitated : pause in indecision before saying or doing something. Synonym of Hesitated is Paused"
    },
    {
        "question": "RESCUE",
        "options": [
            {
                "option": "A.",
                "text": "Save"
            },
            {
                "option": "B.",
                "text": "Command"
            },
            {
                "option": "C.",
                "text": "Help"
            },
            {
                "option": "D.",
                "text": "Defence"
            },
            {
                "option": "E.",
                "text": "None of these"
            }
        ],
        "answer": "Option A",
        "solution": "Answer & Solution Answer: Option A No explanation is given for this question Let's Discuss on Board"
    },
    {
        "question": "ATTEMPT",
        "options": [
            {
                "option": "A.",
                "text": "Serve"
            },
            {
                "option": "B.",
                "text": "Explore"
            },
            {
                "option": "C.",
                "text": "Try"
            },
            {
                "option": "D.",
                "text": "Explain"
            }
        ],
        "answer": "Option C",
        "solution": "Answer & Solution Answer: Option C Solution: Serve : perform duties or services for (another person or an organization). Explore : travel through (an unfamiliar area) in order to learn about it. Try : make an attempt or effort to do something. Explain : make (an idea or situation) clear to someone by describing it in more detail or revealing relevant facts. Attempt : make an effort to achieve or complete (something difficult). Synonym of Attempt is Try"
    },
    {
        "question": "FORAY",
        "options": [
            {
                "option": "A.",
                "text": "Maraud"
            },
            {
                "option": "B.",
                "text": "Contest"
            },
            {
                "option": "C.",
                "text": "Ranger"
            },
            {
                "option": "D.",
                "text": "Intuition"
            }
        ],
        "answer": "Option A",
        "solution": "Answer & Solution Answer: Option A Solution: Maraud : go about in search of things to steal or people to attack. Contest : an event in which people compete for supremacy in a sport or other activity, or in a quality. Ranger : a keeper of a park, forest, or area of countryside. Intuition : the ability to understand something instinctively, without the need for conscious reasoning. Foray : a sudden attack or incursion into enemy territory, especially to obtain something; a raid. Synonym of Foray is Maraud"
    },
    {
        "question": "RECKLESS",
        "options": [
            {
                "option": "A.",
                "text": "Courageous"
            },
            {
                "option": "B.",
                "text": "Rash"
            },
            {
                "option": "C.",
                "text": "Bold"
            },
            {
                "option": "D.",
                "text": "Daring"
            }
        ],
        "answer": "Option B",
        "solution": "Answer & Solution Answer: Option B Solution: Courageous : not deterred by danger or pain; brave. Rash : acting or done without careful consideration of the possible consequences; impetuous. Bold : (of a person, action, or idea) showing a willingness to take risks; confident and courageous. Daring : (of a person or action) adventurous or audaciously bold. Reckless : heedless of danger or the consequences of one's actions; rash or impetuous. Synonym of Rash is Reckless"
    },
    {
        "question": "CONSEQUENCES",
        "options": [
            {
                "option": "A.",
                "text": "Results"
            },
            {
                "option": "B.",
                "text": "Conclusions"
            },
            {
                "option": "C.",
                "text": "Difficulties"
            },
            {
                "option": "D.",
                "text": "Applications"
            }
        ],
        "answer": "Option A",
        "solution": "Answer & Solution Answer: Option A Solution: Results : a thing that is caused or produced by something else; a consequence or outcome. Conclusions : the end or finish of an event, process, or text. Difficulties : the state or condition of being difficult. Applications : a formal request to be considered for a position or to be allowed to do or have something, submitted to an authority, institution, or organization. Consequences : a result or effect, typically one that is unwelcome or unpleasant. Synonym of Consequences is Results"
    },
    {
        "question": "IMPROVEMENT",
        "options": [
            {
                "option": "A.",
                "text": "Advancement"
            },
            {
                "option": "B.",
                "text": "Betterment"
            },
            {
                "option": "C.",
                "text": "Promotion"
            },
            {
                "option": "D.",
                "text": "Preference"
            }
        ],
        "answer": "Option B",
        "solution": "Answer & Solution Answer: Option B Solution: Advancement : the process of promoting a cause or plan. Betterment : the improvement of something. Promotion : activity that supports or encourages a cause, venture, or aim. Preference : a greater liking for one alternative over another or others. Improvement : development; betterment. Synonym of Improvement is Betterment"
    },
    {
        "question": "INEBRIATE",
        "options": [
            {
                "option": "A.",
                "text": "Dreamy"
            },
            {
                "option": "B.",
                "text": "Stupefied"
            },
            {
                "option": "C.",
                "text": "Unsteady"
            },
            {
                "option": "D.",
                "text": "Drunken"
            }
        ],
        "answer": "Option D",
        "solution": "Answer & Solution Answer: Option D Solution: Dreamy : having a magical or pleasantly unreal quality; dreamlike. Stupefied : make (someone) unable to think or feel properly. Unsteady : liable to fall or shake; not steady in position. Drunken : drunk or intoxicated. Inebriate : drunk or intoxicated. Synonym of Inebriate is Drunken"
    },
    {
        "question": "STERILE",
        "options": [
            {
                "option": "A.",
                "text": "Barren"
            },
            {
                "option": "B.",
                "text": "Fertile"
            },
            {
                "option": "C.",
                "text": "Childless"
            },
            {
                "option": "D.",
                "text": "Dry"
            }
        ],
        "answer": "Option A",
        "solution": "Answer & Solution Answer: Option A Solution: Barren : of land) too poor to produce much or any vegetation. Fertile : (of soil or land) producing or capable of producing abundant vegetation or crops. Childless : not having any children. Dry : free from moisture or liquid; not wet or moist. Sterile : (of land or soil) too poor in quality to produce crops. Synonym of Sterile is Barren"
    },
    {
        "question": "ABJECT",
        "options": [
            {
                "option": "A.",
                "text": "Challenge"
            },
            {
                "option": "B.",
                "text": "Miserable"
            },
            {
                "option": "C.",
                "text": "Deny"
            },
            {
                "option": "D.",
                "text": "Disobey"
            }
        ],
        "answer": "Option B",
        "solution": "Answer & Solution Answer: Option B Solution: Challenge : a call to someone to participate in a competitive situation or fight to decide who is superior in terms of ability or strength. Miserable : (of a person) wretchedly unhappy or uncomfortable. Deny : state that one refuses to admit the truth or existence of. Disobey : fail to obey (rules, a command, or someone in authority). Abject : extremely unpleasant and degrading; miserable. Synonym of Abject is Miserable"
    },
    {
        "question": "MOVING",
        "options": [
            {
                "option": "A.",
                "text": "Taking"
            },
            {
                "option": "B.",
                "text": "Toying"
            },
            {
                "option": "C.",
                "text": "Shifting"
            },
            {
                "option": "D.",
                "text": "Turning"
            }
        ],
        "answer": "Option C",
        "solution": "Answer & Solution Answer: Option C Solution: Taking : the action or process of taking something. Toying : move or handle (an object) absent-mindedly or nervously. Shifting : move or cause to move from one place to another, especially over a small distance. Turning : a place where a road branches off from another. Moving : change the place, position, or state of. Synonym of Moving is Shifting"
    },
    {
        "question": "IRONIC",
        "options": [
            {
                "option": "A.",
                "text": "Inflexible"
            },
            {
                "option": "B.",
                "text": "Bitter"
            },
            {
                "option": "C.",
                "text": "Good-natured"
            },
            {
                "option": "D.",
                "text": "Sarcastic"
            }
        ],
        "answer": "Option D",
        "solution": "Answer & Solution Answer: Option D Solution: Inflexible : unwilling to change or compromise. Bitter : having a sharp, pungent taste or smell; not sweet. Good-natured : kind, friendly, and patient. Sarcastic : Ironic. Ironic : marked by or given to using irony in order to mock or convey contempt. Synonym of Ironic is Sarcastic"
    },
    {
        "question": "TIMID",
        "options": [
            {
                "option": "A.",
                "text": "Fast"
            },
            {
                "option": "B.",
                "text": "Slow"
            },
            {
                "option": "C.",
                "text": "Medium"
            },
            {
                "option": "D.",
                "text": "Shy"
            }
        ],
        "answer": "Option D",
        "solution": "Answer & Solution Answer: Option D Solution: Fast : moving or capable of moving at high speed. Slow : moving or operating, or designed to do so, only at a low speed Medium : an agency or means of doing something. Shy : nervous or timid in the company of other people. Timid : showing a lack of courage or confidence. Synonym of Timid is Shy"
    },
    {
        "question": "EXTRICATE",
        "options": [
            {
                "option": "A.",
                "text": "Pull"
            },
            {
                "option": "B.",
                "text": "Free"
            },
            {
                "option": "C.",
                "text": "Tie"
            },
            {
                "option": "D.",
                "text": "Complicate"
            }
        ],
        "answer": "Option B",
        "solution": "Answer & Solution Answer: Option B Solution: Pull : exert force on (someone or something) so as to cause movement towards oneself. Free : release from physical obstruction or restraint. Tie : attach or fasten with string or similar cord. Complicate : make (something) more complicated. Extricate : free (someone or something) from a constraint or difficulty. Synonym of Extricate is Free"
    },
    {
        "question": "NEUTRAL",
        "options": [
            {
                "option": "A.",
                "text": "Unbiased"
            },
            {
                "option": "B.",
                "text": "Non-aligned"
            },
            {
                "option": "C.",
                "text": "Undecided"
            },
            {
                "option": "D.",
                "text": "Indifferent"
            }
        ],
        "answer": "Option A",
        "solution": "Answer & Solution Answer: Option A Solution: Unbiased : Impartial. Non-aligned : Independent. Undecided : (of a person) not having made a decision. Indifferent : having no particular interest or sympathy. Neutral : not supporting or helping either side in a conflict, disagreement, etc. Synonym of Neutral is Unbiased"
    },
    {
        "question": "SHALLOW",
        "options": [
            {
                "option": "A.",
                "text": "Artificial"
            },
            {
                "option": "B.",
                "text": "Superficial"
            },
            {
                "option": "C.",
                "text": "Foolish"
            },
            {
                "option": "D.",
                "text": "Worthless"
            }
        ],
        "answer": "Option B",
        "solution": "Answer & Solution Answer: Option B Solution: Artificial : made or produced by human beings rather than occurring naturally, especially as a copy of something natural. Superficial : appearing to be true or real only until examined more closely. Foolish : lacking good sense or judgement; unwise. Worthless : having no real value or use. Shallow : not exhibiting, requiring, or capable of serious thought. Synonym of Shallow is Superficial"
    },
    {
        "question": "DIVERSION",
        "options": [
            {
                "option": "A.",
                "text": "Amusement"
            },
            {
                "option": "B.",
                "text": "Arrival"
            },
            {
                "option": "C.",
                "text": "Deviation"
            },
            {
                "option": "D.",
                "text": "Bylane"
            }
        ],
        "answer": "Option C",
        "solution": "Answer & Solution Answer: Option C Solution: Amusement : the state or experience of finding something funny. Arrival : the action or process of arriving. Deviation : the action of departing from an established course or accepted standard. Bylane : a side lane or alley off a road. Diversion : the action of turning something aside from its course. Synonym of Diversion is Deviation"
    },
    {
        "question": "INSOLVENT",
        "options": [
            {
                "option": "A.",
                "text": "Poor"
            },
            {
                "option": "B.",
                "text": "Bankrupt"
            },
            {
                "option": "C.",
                "text": "Penniless"
            },
            {
                "option": "D.",
                "text": "Broke"
            }
        ],
        "answer": "Option B",
        "solution": "Answer & Solution Answer: Option B Solution: Poor : lacking sufficient money to live at a standard considered comfortable or normal in a society. Bankrupt : (of a person or organization) declared in law as unable to pay their debts. Penniless : (of a person) having no money; very poor. Broke : having completely run out of money. Insolvent : unable to pay debts owed. Synonym of Insolvent is Bankrupt"
    },
    {
        "question": "INEXPLICABLE",
        "options": [
            {
                "option": "A.",
                "text": "Confusing"
            },
            {
                "option": "B.",
                "text": "Unaccountable"
            },
            {
                "option": "C.",
                "text": "Chaotic"
            },
            {
                "option": "D.",
                "text": "Unconnected"
            }
        ],
        "answer": "Option B",
        "solution": "Answer & Solution Answer: Option B Solution: Confusing : bewildering or perplexing. Unaccountable : unable to be explained. Chaotic : in a state of complete confusion and disorder. Unconnected : not joined together or to something else. Inexplicable : unable to be explained or accounted for. Synonym of Inexplicable is Unaccountable"
    },
    {
        "question": "FEEBLE",
        "options": [
            {
                "option": "A.",
                "text": "Weak"
            },
            {
                "option": "B.",
                "text": "Vain"
            },
            {
                "option": "C.",
                "text": "Arrogant"
            },
            {
                "option": "D.",
                "text": "Sick"
            }
        ],
        "answer": "Option A",
        "solution": "Answer & Solution Answer: Option A Solution: Weak : lacking the power to perform physically demanding tasks. Vain : having or showing an excessively high opinion of one's appearance, abilities, or worth. Arrogant : having or revealing an exaggerated sense of one's own importance or abilities. Sick : affected by physical or mental illness. Feeble : lacking physical strength, especially as a result of age or illness. Synonym of Feeble is Weak"
    },
    {
        "question": "TRANSIENT",
        "options": [
            {
                "option": "A.",
                "text": "Transparent"
            },
            {
                "option": "B.",
                "text": "Fleeting"
            },
            {
                "option": "C.",
                "text": "Feeble"
            },
            {
                "option": "D.",
                "text": "Fanciful"
            }
        ],
        "answer": "Option B",
        "solution": "Answer & Solution Answer: Option B Solution: Transparent : (of a material or article) allowing light to pass through so that objects behind can be distinctly seen. Fleeting : lasting for a very short time. Feeble : lacking physical strength, especially as a result of age or illness. Fanciful : over-imaginative and unrealistic. Transient : lasting for a very short time. Synonym of Transient is Fleeting"
    },
    {
        "question": "BARE",
        "options": [
            {
                "option": "A.",
                "text": "Uncovered"
            },
            {
                "option": "B.",
                "text": "Tolerate"
            },
            {
                "option": "C.",
                "text": "Clear"
            },
            {
                "option": "D.",
                "text": "Neat"
            }
        ],
        "answer": "Option A",
        "solution": "Answer & Solution Answer: Option A Solution: Uncovered : not covered. Tolerate : allow the existence, occurrence, or practice of (something that one dislikes or disagrees with) without interference. Clear : easy to perceive, understand, or interpret. Neat : arranged in a tidy way; in good order. Bare : not clothed or covered. Synonym of Bare is Uncovered"
    },
    {
        "question": "REPEAL",
        "options": [
            {
                "option": "A.",
                "text": "Sanction"
            },
            {
                "option": "B.",
                "text": "Perpetuate"
            },
            {
                "option": "C.",
                "text": "Pass"
            },
            {
                "option": "D.",
                "text": "Cancel"
            }
        ],
        "answer": "Option D",
        "solution": "Answer & Solution Answer: Option D Solution: Sanction : a threatened penalty for disobeying a law or rule. Perpetuate : make (something) continue indefinitely. Pass : move or cause to move in a specified direction. Cancel : decide or announce that (a planned event) will not take place. Repeal : cancellation. Synonym of Repeal is Cancel"
    },
    {
        "question": "SALACITY",
        "options": [
            {
                "option": "A.",
                "text": "Bliss"
            },
            {
                "option": "B.",
                "text": "Depression"
            },
            {
                "option": "C.",
                "text": "Indecency"
            },
            {
                "option": "D.",
                "text": "Recession"
            }
        ],
        "answer": "Option C",
        "solution": "Answer & Solution Answer: Option C Solution: Bliss : perfect happiness; great joy. Depression : feelings of severe despondency and dejection. Indecency : an indecent act or expression. Recession : a period of temporary economic decline during which trade and industrial activity are reduced, generally identified by a fall in GDP in two successive quarters. Salacity : the expression of undue or inappropriate interest in sexual matters. Synonym of Salacity is Indecency"
    },
    {
        "question": "ECSTATIC",
        "options": [
            {
                "option": "A.",
                "text": "Animated"
            },
            {
                "option": "B.",
                "text": "Bewildered"
            },
            {
                "option": "C.",
                "text": "Enraptured"
            },
            {
                "option": "D.",
                "text": "Willful"
            }
        ],
        "answer": "Option C",
        "solution": "Answer & Solution Answer: Option C Solution: Animated : full of life or excitement; lively. Bewildered : perplexed and confused; very puzzled. Enraptured : give intense pleasure or joy to. Willful : (of a bad or harmful act) intentional; deliberate. Ecstatic : feeling or expressing overwhelming happiness or joyful excitement. Synonym of Ecstatic is Enraptured"
    }
]