[
    {
        "question": "She's angry . . . . . . . . you.",
        "options": [
            {
                "option": "A.",
                "text": "on"
            },
            {
                "option": "B.",
                "text": "for"
            },
            {
                "option": "C.",
                "text": "with"
            },
            {
                "option": "D.",
                "text": "to"
            }
        ],
        "answer": "Option C",
        "solution": "Answer & Solution Answer: Option C No explanation is given for this question Let's Discuss on Board"
    },
    {
        "question": "No one can hinder him . . . . . . . . me in the maket.",
        "options": [
            {
                "option": "A.",
                "text": "into"
            },
            {
                "option": "B.",
                "text": "from"
            },
            {
                "option": "C.",
                "text": "of"
            },
            {
                "option": "D.",
                "text": "at"
            }
        ],
        "answer": "Option B",
        "solution": "Answer & Solution Answer: Option B No explanation is given for this question Let's Discuss on Board"
    },
    {
        "question": "We will never play . . . . . . . . you.",
        "options": [
            {
                "option": "A.",
                "text": "to"
            },
            {
                "option": "B.",
                "text": "beside"
            },
            {
                "option": "C.",
                "text": "with"
            },
            {
                "option": "D.",
                "text": "None of these"
            }
        ],
        "answer": "Option C",
        "solution": "Answer & Solution Answer: Option C No explanation is given for this question Let's Discuss on Board"
    },
    {
        "question": "Let's discuss . . . . . . . . the ways of improving the basic skills of English.",
        "options": [
            {
                "option": "A.",
                "text": "about"
            },
            {
                "option": "B.",
                "text": "on"
            },
            {
                "option": "C.",
                "text": "of"
            },
            {
                "option": "D.",
                "text": "no preposition"
            }
        ],
        "answer": "Option D",
        "solution": "Answer & Solution Answer: Option D No explanation is given for this question Let's Discuss on Board"
    },
    {
        "question": "He insists . . . . . . . . leaving immediately.",
        "options": [
            {
                "option": "A.",
                "text": "against"
            },
            {
                "option": "B.",
                "text": "over"
            },
            {
                "option": "C.",
                "text": "for"
            },
            {
                "option": "D.",
                "text": "on"
            }
        ],
        "answer": "Option D",
        "solution": "Answer & Solution Answer: Option D No explanation is given for this question Let's Discuss on Board"
    },
    {
        "question": "Please bear . . . . . . . . me until I finish this job.",
        "options": [
            {
                "option": "A.",
                "text": "of"
            },
            {
                "option": "B.",
                "text": "with"
            },
            {
                "option": "C.",
                "text": "in"
            },
            {
                "option": "D.",
                "text": "off"
            }
        ],
        "answer": "Option B",
        "solution": "Answer & Solution Answer: Option B No explanation is given for this question Let's Discuss on Board"
    },
    {
        "question": "You have to be . . . . . . . . 18 to see this film.",
        "options": [
            {
                "option": "A.",
                "text": "at"
            },
            {
                "option": "B.",
                "text": "over"
            },
            {
                "option": "C.",
                "text": "of"
            },
            {
                "option": "D.",
                "text": "on"
            }
        ],
        "answer": "Option B",
        "solution": "Answer & Solution Answer: Option B No explanation is given for this question Let's Discuss on Board"
    },
    {
        "question": "I am good . . . . . . . . tennis.",
        "options": [
            {
                "option": "A.",
                "text": "about"
            },
            {
                "option": "B.",
                "text": "in"
            },
            {
                "option": "C.",
                "text": "at"
            },
            {
                "option": "D.",
                "text": "of"
            }
        ],
        "answer": "Option C",
        "solution": "Answer & Solution Answer: Option C No explanation is given for this question Let's Discuss on Board"
    },
    {
        "question": "The lady curried her handbag . . . . . . . . her arm.",
        "options": [
            {
                "option": "A.",
                "text": "in"
            },
            {
                "option": "B.",
                "text": "over"
            },
            {
                "option": "C.",
                "text": "on"
            },
            {
                "option": "D.",
                "text": "under"
            }
        ],
        "answer": "Option D",
        "solution": "Answer & Solution Answer: Option D No explanation is given for this question Let's Discuss on Board"
    },
    {
        "question": "your success is . . . . . . . . your hard work.",
        "options": [
            {
                "option": "A.",
                "text": "due to"
            },
            {
                "option": "B.",
                "text": "instead of"
            },
            {
                "option": "C.",
                "text": "at the top of"
            },
            {
                "option": "D.",
                "text": "in spite of"
            }
        ],
        "answer": "Option A",
        "solution": "Answer & Solution Answer: Option A No explanation is given for this question Let's Discuss on Board"
    },
    {
        "question": "The Quaid-e-Azam worked hard . . . . . . . . his homeland.",
        "options": [
            {
                "option": "A.",
                "text": "in"
            },
            {
                "option": "B.",
                "text": "with"
            },
            {
                "option": "C.",
                "text": "for"
            },
            {
                "option": "D.",
                "text": "about"
            }
        ],
        "answer": "Option C",
        "solution": "Answer & Solution Answer: Option C No explanation is given for this question Let's Discuss on Board"
    },
    {
        "question": "I am just going out to shop. I'll be back . . . . . . . . about 15 minutes.",
        "options": [
            {
                "option": "A.",
                "text": "on"
            },
            {
                "option": "B.",
                "text": "in"
            },
            {
                "option": "C.",
                "text": "within"
            },
            {
                "option": "D.",
                "text": "for"
            }
        ],
        "answer": "Option B",
        "solution": "Answer & Solution Answer: Option B No explanation is given for this question Let's Discuss on Board"
    },
    {
        "question": "I could not find the solution . . . . . . . . the problem.",
        "options": [
            {
                "option": "A.",
                "text": "about"
            },
            {
                "option": "B.",
                "text": "in"
            },
            {
                "option": "C.",
                "text": "to"
            },
            {
                "option": "D.",
                "text": "of"
            }
        ],
        "answer": "Option C",
        "solution": "Answer & Solution Answer: Option C Solution: The correct answer is C: to Let's break down why: We're looking for the preposition that correctly connects \"solution\" with \"the problem.\" The phrase \"solution to something\" is a very common and correct usage in English. It means the answer or way out to a problem or situation. Let's look at why the other options don't work as well: A: about - \"Solution about the problem\" doesn't sound natural. While \"about\" can indicate the topic, it's not the correct preposition for a solution. B: in - \"Solution in the problem\" implies that the solution is somehow contained within the problem itself, which doesn't make logical sense. We find a solution to, not in, a problem. D: of - \"Solution of the problem\" is grammatically incorrect in this context. While \"of\" can show a relationship, it's not the idiomatic way to express finding an answer to a specific issue. Therefore, \"I could not find the solution to the problem\" is the most natural and correct sentence."
    },
    {
        "question": "Spring comes . . . . . . . . winter.",
        "options": [
            {
                "option": "A.",
                "text": "on"
            },
            {
                "option": "B.",
                "text": "after"
            },
            {
                "option": "C.",
                "text": "in"
            },
            {
                "option": "D.",
                "text": "at"
            }
        ],
        "answer": "Option B",
        "solution": "Answer & Solution Answer: Option B No explanation is given for this question Let's Discuss on Board"
    },
    {
        "question": "The book is . . . . . . . . the mug and the pen.",
        "options": [
            {
                "option": "A.",
                "text": "on"
            },
            {
                "option": "B.",
                "text": "between"
            },
            {
                "option": "C.",
                "text": "in"
            },
            {
                "option": "D.",
                "text": "None of the above"
            }
        ],
        "answer": "Option B",
        "solution": "Answer & Solution Answer: Option B No explanation is given for this question Let's Discuss on Board"
    },
    {
        "question": "The cow is standing . . . . . . . . the tree.",
        "options": [
            {
                "option": "A.",
                "text": "into"
            },
            {
                "option": "B.",
                "text": "on"
            },
            {
                "option": "C.",
                "text": "in"
            },
            {
                "option": "D.",
                "text": "under"
            }
        ],
        "answer": "Option D",
        "solution": "Answer & Solution Answer: Option D No explanation is given for this question Let's Discuss on Board"
    },
    {
        "question": "The two were found guilty of robbery and condemned . . . . . . . . four years imprisonment.",
        "options": [
            {
                "option": "A.",
                "text": "with"
            },
            {
                "option": "B.",
                "text": "for"
            },
            {
                "option": "C.",
                "text": "to"
            },
            {
                "option": "D.",
                "text": "of"
            }
        ],
        "answer": "Option C",
        "solution": "Answer & Solution Answer: Option C No explanation is given for this question Let's Discuss on Board"
    },
    {
        "question": "My holidays will start . . . . . . . . 23rd May.",
        "options": [
            {
                "option": "A.",
                "text": "in"
            },
            {
                "option": "B.",
                "text": "from"
            },
            {
                "option": "C.",
                "text": "on"
            },
            {
                "option": "D.",
                "text": "under"
            }
        ],
        "answer": "Option B",
        "solution": "Answer & Solution Answer: Option B No explanation is given for this question Let's Discuss on Board"
    },
    {
        "question": "Everything is . . . . . . . . control there is no need to worry.",
        "options": [
            {
                "option": "A.",
                "text": "about"
            },
            {
                "option": "B.",
                "text": "under"
            },
            {
                "option": "C.",
                "text": "in"
            },
            {
                "option": "D.",
                "text": "of"
            }
        ],
        "answer": "Option B",
        "solution": "Answer & Solution Answer: Option B No explanation is given for this question Let's Discuss on Board"
    },
    {
        "question": "The goods that had not been claimed were sold . . . . . . . . the Police Property Act.",
        "options": [
            {
                "option": "A.",
                "text": "in"
            },
            {
                "option": "B.",
                "text": "under"
            },
            {
                "option": "C.",
                "text": "of"
            },
            {
                "option": "D.",
                "text": "about"
            }
        ],
        "answer": "Option B",
        "solution": "Answer & Solution Answer: Option B No explanation is given for this question Let's Discuss on Board"
    },
    {
        "question": "I finally received the letter which I had been waiting . . . . . . . . .",
        "options": [
            {
                "option": "A.",
                "text": "for"
            },
            {
                "option": "B.",
                "text": "at"
            },
            {
                "option": "C.",
                "text": "on"
            },
            {
                "option": "D.",
                "text": "to"
            }
        ],
        "answer": "Option A",
        "solution": "Answer & Solution Answer: Option A No explanation is given for this question Let's Discuss on Board"
    },
    {
        "question": "I feel that she is unhappy . . . . . . . . her poor grades.",
        "options": [
            {
                "option": "A.",
                "text": "on"
            },
            {
                "option": "B.",
                "text": "at"
            },
            {
                "option": "C.",
                "text": "over"
            },
            {
                "option": "D.",
                "text": "with"
            }
        ],
        "answer": "Option D",
        "solution": "Answer & Solution Answer: Option D No explanation is given for this question Let's Discuss on Board"
    },
    {
        "question": ". . . . . . . . whom are you talking?",
        "options": [
            {
                "option": "A.",
                "text": "to"
            },
            {
                "option": "B.",
                "text": "too"
            },
            {
                "option": "C.",
                "text": "by"
            },
            {
                "option": "D.",
                "text": "over"
            }
        ],
        "answer": "Option A",
        "solution": "Answer & Solution Answer: Option A No explanation is given for this question Let's Discuss on Board"
    },
    {
        "question": "This record enables me to balance . . . . . . . . the facts of my life and decide what to do with it.",
        "options": [
            {
                "option": "A.",
                "text": "up"
            },
            {
                "option": "B.",
                "text": "on"
            },
            {
                "option": "C.",
                "text": "down"
            },
            {
                "option": "D.",
                "text": "of"
            }
        ],
        "answer": "Option A",
        "solution": "Answer & Solution Answer: Option A No explanation is given for this question Let's Discuss on Board"
    },
    {
        "question": "He is not sitting . . . . . . . . his desk but . . . . . . . . his armchair.",
        "options": [
            {
                "option": "A.",
                "text": "with, on"
            },
            {
                "option": "B.",
                "text": "on, on"
            },
            {
                "option": "C.",
                "text": "at, in"
            },
            {
                "option": "D.",
                "text": "at, on"
            }
        ],
        "answer": "Option C",
        "solution": "Answer & Solution Answer: Option C No explanation is given for this question Let's Discuss on Board"
    },
    {
        "question": "\"Please look . . . . . . . . my baby for me,\" the lady said.",
        "options": [
            {
                "option": "A.",
                "text": "after"
            },
            {
                "option": "B.",
                "text": "over"
            },
            {
                "option": "C.",
                "text": "again"
            },
            {
                "option": "D.",
                "text": "before"
            }
        ],
        "answer": "Option A",
        "solution": "Answer & Solution Answer: Option A No explanation is given for this question Let's Discuss on Board"
    },
    {
        "question": "She was looking . . . . . . . . me.",
        "options": [
            {
                "option": "A.",
                "text": "in"
            },
            {
                "option": "B.",
                "text": "at"
            },
            {
                "option": "C.",
                "text": "to"
            },
            {
                "option": "D.",
                "text": "None of the above"
            }
        ],
        "answer": "Option B",
        "solution": "Answer & Solution Answer: Option B No explanation is given for this question Let's Discuss on Board"
    },
    {
        "question": "If the fire-station had been got on . . . . . . . . at once, the hotel might have been saved.",
        "options": [
            {
                "option": "A.",
                "text": "to"
            },
            {
                "option": "B.",
                "text": "into"
            },
            {
                "option": "C.",
                "text": "with"
            },
            {
                "option": "D.",
                "text": "from"
            }
        ],
        "answer": "Option A",
        "solution": "Answer & Solution Answer: Option A No explanation is given for this question Let's Discuss on Board"
    },
    {
        "question": "The terrorist shot the policeman . . . . . . . . his gun.",
        "options": [
            {
                "option": "A.",
                "text": "in"
            },
            {
                "option": "B.",
                "text": "with"
            },
            {
                "option": "C.",
                "text": "for"
            },
            {
                "option": "D.",
                "text": "by"
            }
        ],
        "answer": "Option B",
        "solution": "Answer & Solution Answer: Option B No explanation is given for this question Let's Discuss on Board"
    },
    {
        "question": "He divided the money . . . . . . . . the two children.",
        "options": [
            {
                "option": "A.",
                "text": "among"
            },
            {
                "option": "B.",
                "text": "between"
            },
            {
                "option": "C.",
                "text": "in between"
            },
            {
                "option": "D.",
                "text": "over"
            }
        ],
        "answer": "Option B",
        "solution": "Answer & Solution Answer: Option B No explanation is given for this question Let's Discuss on Board"
    },
    {
        "question": "He put the pot . . . . . . . . the table.",
        "options": [
            {
                "option": "A.",
                "text": "on"
            },
            {
                "option": "B.",
                "text": "to"
            },
            {
                "option": "C.",
                "text": "in"
            },
            {
                "option": "D.",
                "text": "out"
            }
        ],
        "answer": "Option A",
        "solution": "Answer & Solution Answer: Option A No explanation is given for this question Let's Discuss on Board"
    },
    {
        "question": "I am much ashamed . . . . . . . . my son.",
        "options": [
            {
                "option": "A.",
                "text": "by"
            },
            {
                "option": "B.",
                "text": "of"
            },
            {
                "option": "C.",
                "text": "at"
            },
            {
                "option": "D.",
                "text": "on"
            }
        ],
        "answer": "Option B",
        "solution": "Answer & Solution Answer: Option B No explanation is given for this question Let's Discuss on Board"
    },
    {
        "question": "In this engine the rotary section corresponds . . . . . . . . the cylinders of conventional model.",
        "options": [
            {
                "option": "A.",
                "text": "to"
            },
            {
                "option": "B.",
                "text": "with"
            },
            {
                "option": "C.",
                "text": "in"
            },
            {
                "option": "D.",
                "text": "on"
            }
        ],
        "answer": "Option A",
        "solution": "Answer & Solution Answer: Option A No explanation is given for this question Let's Discuss on Board"
    },
    {
        "question": "He accused the man . . . . . . . . stealing.",
        "options": [
            {
                "option": "A.",
                "text": "for"
            },
            {
                "option": "B.",
                "text": "on"
            },
            {
                "option": "C.",
                "text": "with"
            },
            {
                "option": "D.",
                "text": "of"
            }
        ],
        "answer": "Option D",
        "solution": "Answer & Solution Answer: Option D No explanation is given for this question Let's Discuss on Board"
    },
    {
        "question": "Kamini was so angry that she threw a stone . . . . . . . . Manan.",
        "options": [
            {
                "option": "A.",
                "text": "into"
            },
            {
                "option": "B.",
                "text": "to"
            },
            {
                "option": "C.",
                "text": "at"
            },
            {
                "option": "D.",
                "text": "by"
            }
        ],
        "answer": "Option C",
        "solution": "Answer & Solution Answer: Option C No explanation is given for this question Let's Discuss on Board"
    },
    {
        "question": "\"The price of prawns has gone . . . . . . . . a lot. They cost so much these days,\" Mrs. Lee said.",
        "options": [
            {
                "option": "A.",
                "text": "up"
            },
            {
                "option": "B.",
                "text": "over"
            },
            {
                "option": "C.",
                "text": "under"
            },
            {
                "option": "D.",
                "text": "below"
            }
        ],
        "answer": "Option A",
        "solution": "Answer & Solution Answer: Option A No explanation is given for this question Let's Discuss on Board"
    },
    {
        "question": "Their relationship was . . . . . . . . because of jealousy.",
        "options": [
            {
                "option": "A.",
                "text": "in"
            },
            {
                "option": "B.",
                "text": "over"
            },
            {
                "option": "C.",
                "text": "on"
            },
            {
                "option": "D.",
                "text": "of"
            }
        ],
        "answer": "Option B",
        "solution": "Answer & Solution Answer: Option B No explanation is given for this question Let's Discuss on Board"
    },
    {
        "question": "There is no doubt that Adam is very good . . . . . . . . telling jokes.",
        "options": [
            {
                "option": "A.",
                "text": "over"
            },
            {
                "option": "B.",
                "text": "at"
            },
            {
                "option": "C.",
                "text": "of"
            },
            {
                "option": "D.",
                "text": "with"
            }
        ],
        "answer": "Option B",
        "solution": "Answer & Solution Answer: Option B No explanation is given for this question Let's Discuss on Board"
    },
    {
        "question": "We traveled to Lipoh . . . . . . . . bus.",
        "options": [
            {
                "option": "A.",
                "text": "by"
            },
            {
                "option": "B.",
                "text": "on"
            },
            {
                "option": "C.",
                "text": "at"
            },
            {
                "option": "D.",
                "text": "in"
            }
        ],
        "answer": "Option A",
        "solution": "Answer & Solution Answer: Option A No explanation is given for this question Let's Discuss on Board"
    },
    {
        "question": "There is something very attractive . . . . . . . . him.",
        "options": [
            {
                "option": "A.",
                "text": "in"
            },
            {
                "option": "B.",
                "text": "about"
            },
            {
                "option": "C.",
                "text": "by"
            },
            {
                "option": "D.",
                "text": "with"
            }
        ],
        "answer": "Option B",
        "solution": "Answer & Solution Answer: Option B No explanation is given for this question Let's Discuss on Board"
    },
    {
        "question": "Distribute the sweets . . . . . . . . the two children.",
        "options": [
            {
                "option": "A.",
                "text": "both"
            },
            {
                "option": "B.",
                "text": "above"
            },
            {
                "option": "C.",
                "text": "among"
            },
            {
                "option": "D.",
                "text": "between"
            }
        ],
        "answer": "Option D",
        "solution": "Answer & Solution Answer: Option D No explanation is given for this question Let's Discuss on Board"
    },
    {
        "question": "He is jealous . . . . . . . . her success.",
        "options": [
            {
                "option": "A.",
                "text": "about"
            },
            {
                "option": "B.",
                "text": "of"
            },
            {
                "option": "C.",
                "text": "in"
            },
            {
                "option": "D.",
                "text": "on"
            }
        ],
        "answer": "Option B",
        "solution": "Answer & Solution Answer: Option B No explanation is given for this question Let's Discuss on Board"
    },
    {
        "question": "We must keep . . . . . . . . something for the rainy day.",
        "options": [
            {
                "option": "A.",
                "text": "by"
            },
            {
                "option": "B.",
                "text": "in"
            },
            {
                "option": "C.",
                "text": "for"
            },
            {
                "option": "D.",
                "text": "at"
            }
        ],
        "answer": "Option B",
        "solution": "Answer & Solution Answer: Option B No explanation is given for this question Let's Discuss on Board"
    },
    {
        "question": "We don't agree . . . . . . . . anything but we're good friends.",
        "options": [
            {
                "option": "A.",
                "text": "on"
            },
            {
                "option": "B.",
                "text": "in"
            },
            {
                "option": "C.",
                "text": "of"
            },
            {
                "option": "D.",
                "text": "for"
            }
        ],
        "answer": "Option A",
        "solution": "Answer & Solution Answer: Option A No explanation is given for this question Let's Discuss on Board"
    },
    {
        "question": "Minority aspirations cannot forever be kept in check . . . . . . . . the gun.",
        "options": [
            {
                "option": "A.",
                "text": "with"
            },
            {
                "option": "B.",
                "text": "by"
            },
            {
                "option": "C.",
                "text": "under"
            },
            {
                "option": "D.",
                "text": "through"
            }
        ],
        "answer": "Option A",
        "solution": "Answer & Solution Answer: Option A No explanation is given for this question Let's Discuss on Board"
    },
    {
        "question": "What is the matter . . . . . . . . her?",
        "options": [
            {
                "option": "A.",
                "text": "of"
            },
            {
                "option": "B.",
                "text": "about"
            },
            {
                "option": "C.",
                "text": "with"
            },
            {
                "option": "D.",
                "text": "on"
            }
        ],
        "answer": "Option C",
        "solution": "Answer & Solution Answer: Option C No explanation is given for this question Let's Discuss on Board"
    },
    {
        "question": "My relations . . . . . . . . Sangeeta are good.",
        "options": [
            {
                "option": "A.",
                "text": "against"
            },
            {
                "option": "B.",
                "text": "on"
            },
            {
                "option": "C.",
                "text": "with"
            },
            {
                "option": "D.",
                "text": "to"
            }
        ],
        "answer": "Option C",
        "solution": "Answer & Solution Answer: Option C No explanation is given for this question Let's Discuss on Board"
    },
    {
        "question": "He always insisted . . . . . . . . his opinion.",
        "options": [
            {
                "option": "A.",
                "text": "to"
            },
            {
                "option": "B.",
                "text": "in"
            },
            {
                "option": "C.",
                "text": "on"
            },
            {
                "option": "D.",
                "text": "over"
            }
        ],
        "answer": "Option C",
        "solution": "Answer & Solution Answer: Option C No explanation is given for this question Let's Discuss on Board"
    },
    {
        "question": "The tiger jumped . . . . . . . . the stag.",
        "options": [
            {
                "option": "A.",
                "text": "on"
            },
            {
                "option": "B.",
                "text": "at"
            },
            {
                "option": "C.",
                "text": "up"
            },
            {
                "option": "D.",
                "text": "onto"
            }
        ],
        "answer": "Option D",
        "solution": "Answer & Solution Answer: Option D No explanation is given for this question Let's Discuss on Board"
    },
    {
        "question": "I am afraid . . . . . . . . snakes.",
        "options": [
            {
                "option": "A.",
                "text": "of"
            },
            {
                "option": "B.",
                "text": "on"
            },
            {
                "option": "C.",
                "text": "with"
            },
            {
                "option": "D.",
                "text": "against"
            }
        ],
        "answer": "Option A",
        "solution": "Answer & Solution Answer: Option A No explanation is given for this question Let's Discuss on Board"
    },
    {
        "question": "I shall leave for Mumbai . . . . . . . . 6 o'clock in the morning.",
        "options": [
            {
                "option": "A.",
                "text": "at"
            },
            {
                "option": "B.",
                "text": "in"
            },
            {
                "option": "C.",
                "text": "on"
            },
            {
                "option": "D.",
                "text": "of"
            }
        ],
        "answer": "Option A",
        "solution": "Answer & Solution Answer: Option A No explanation is given for this question Let's Discuss on Board"
    },
    {
        "question": "He will be cured . . . . . . . . this disease at the earliest.",
        "options": [
            {
                "option": "A.",
                "text": "of"
            },
            {
                "option": "B.",
                "text": "for"
            },
            {
                "option": "C.",
                "text": "from"
            },
            {
                "option": "D.",
                "text": "off"
            }
        ],
        "answer": "Option A",
        "solution": "Answer & Solution Answer: Option A No explanation is given for this question Let's Discuss on Board"
    },
    {
        "question": "She is very poor . . . . . . . . Mathematics.",
        "options": [
            {
                "option": "A.",
                "text": "at"
            },
            {
                "option": "B.",
                "text": "on"
            },
            {
                "option": "C.",
                "text": "for"
            },
            {
                "option": "D.",
                "text": "with"
            }
        ],
        "answer": "Option A",
        "solution": "Answer & Solution Answer: Option A No explanation is given for this question Let's Discuss on Board"
    },
    {
        "question": "It is . . . . . . . . order but delivery can take up to 8 days.",
        "options": [
            {
                "option": "A.",
                "text": "about"
            },
            {
                "option": "B.",
                "text": "in"
            },
            {
                "option": "C.",
                "text": "on"
            },
            {
                "option": "D.",
                "text": "of"
            }
        ],
        "answer": "Option C",
        "solution": "Answer & Solution Answer: Option C No explanation is given for this question Let's Discuss on Board"
    },
    {
        "question": "The mouse is . . . . . . . . the cats.",
        "options": [
            {
                "option": "A.",
                "text": "between"
            },
            {
                "option": "B.",
                "text": "above"
            },
            {
                "option": "C.",
                "text": "on"
            },
            {
                "option": "D.",
                "text": "None of the above"
            }
        ],
        "answer": "Option A",
        "solution": "Answer & Solution Answer: Option A No explanation is given for this question Let's Discuss on Board"
    },
    {
        "question": "He is sitting . . . . . . . . the park.",
        "options": [
            {
                "option": "A.",
                "text": "in"
            },
            {
                "option": "B.",
                "text": "on"
            },
            {
                "option": "C.",
                "text": "at"
            },
            {
                "option": "D.",
                "text": "after"
            }
        ],
        "answer": "Option A",
        "solution": "Answer & Solution Answer: Option A Solution: The correct answer is A: in. Let's understand why: * Prepositions are words that show the relationship between a noun or pronoun and other words in a sentence. They often indicate location, direction, or time. * \"In\" is generally used to describe something located inside a larger area or space. Example: \"The cat is in the house.\" (The cat is within the boundaries of the house). * A park is a relatively large, enclosed area. Therefore, someone sitting in the park is located within the park's boundaries. * \"On\" is usually used for surfaces. Example: \"The book is on the table.\" (The book is resting on the surface of the table). * \"At\" is used for specific points or addresses. Example: \"I'll meet you at the corner.\" (A specific location). * \"After\" indicates time or sequence. Example: \"We'll go after dinner.\" (Following a specific time). In the given sentence, \"in\" is the best preposition to show that the person is sitting within the park's area."
    },
    {
        "question": "Jeanne was texting her boyfriend . . . . . . . . the teacher was teaching.",
        "options": [
            {
                "option": "A.",
                "text": "while"
            },
            {
                "option": "B.",
                "text": "until"
            },
            {
                "option": "C.",
                "text": "of"
            },
            {
                "option": "D.",
                "text": "for"
            }
        ],
        "answer": "Option A",
        "solution": "Answer & Solution Answer: Option A No explanation is given for this question Let's Discuss on Board"
    },
    {
        "question": "Protyush will go to Delhi . . . . . . . . the new year.",
        "options": [
            {
                "option": "A.",
                "text": "on"
            },
            {
                "option": "B.",
                "text": "at"
            },
            {
                "option": "C.",
                "text": "in"
            },
            {
                "option": "D.",
                "text": "to"
            }
        ],
        "answer": "Option B",
        "solution": "Answer & Solution Answer: Option B No explanation is given for this question Let's Discuss on Board"
    },
    {
        "question": "The candidates shall abide . . . . . . . . all directions, instructions and regulations issued by the department.",
        "options": [
            {
                "option": "A.",
                "text": "on"
            },
            {
                "option": "B.",
                "text": "with"
            },
            {
                "option": "C.",
                "text": "by"
            },
            {
                "option": "D.",
                "text": "to"
            }
        ],
        "answer": "Option C",
        "solution": "Answer & Solution Answer: Option C No explanation is given for this question Let's Discuss on Board"
    },
    {
        "question": "The fire gave . . . . . . . . such dense smoke that some firemen backed . . . . . . . . from the burning building.",
        "options": [
            {
                "option": "A.",
                "text": "off, but"
            },
            {
                "option": "B.",
                "text": "in, off"
            },
            {
                "option": "C.",
                "text": "out, away"
            },
            {
                "option": "D.",
                "text": "away, over"
            }
        ],
        "answer": "Option C",
        "solution": "Answer & Solution Answer: Option C No explanation is given for this question Let's Discuss on Board"
    },
    {
        "question": "The load is too heavy . . . . . . . . lift.",
        "options": [
            {
                "option": "A.",
                "text": "from"
            },
            {
                "option": "B.",
                "text": "at"
            },
            {
                "option": "C.",
                "text": "to"
            },
            {
                "option": "D.",
                "text": "by"
            }
        ],
        "answer": "Option C",
        "solution": "Answer & Solution Answer: Option C No explanation is given for this question Let's Discuss on Board"
    },
    {
        "question": "I'll be taking my holiday . . . . . . . . Christmas this year.",
        "options": [
            {
                "option": "A.",
                "text": "on"
            },
            {
                "option": "B.",
                "text": "in"
            },
            {
                "option": "C.",
                "text": "at"
            },
            {
                "option": "D.",
                "text": "None of the above"
            }
        ],
        "answer": "Option A",
        "solution": "Answer & Solution Answer: Option A Solution: The correct preposition to use in this sentence is on. The sentence should read: \"I'll be taking my holiday on Christmas this year.\" The preposition \"on\" is used to indicate a specific day or date when an event will happen. The other options are not suitable in this context: B. \"in Christmas\" (Incorrect) C. \"at Christmas\" (Incorrect) D. None of the above"
    },
    {
        "question": "Is this the book you spoke . . . . . . . . yesterday?",
        "options": [
            {
                "option": "A.",
                "text": "of"
            },
            {
                "option": "B.",
                "text": "on"
            },
            {
                "option": "C.",
                "text": "for"
            },
            {
                "option": "D.",
                "text": "over"
            }
        ],
        "answer": "Option A",
        "solution": "Answer & Solution Answer: Option A No explanation is given for this question Let's Discuss on Board"
    },
    {
        "question": "Maria came to Sydney . . . . . . . . six years.",
        "options": [
            {
                "option": "A.",
                "text": "on"
            },
            {
                "option": "B.",
                "text": "after"
            },
            {
                "option": "C.",
                "text": "in"
            },
            {
                "option": "D.",
                "text": "of"
            }
        ],
        "answer": "Option B",
        "solution": "Answer & Solution Answer: Option B No explanation is given for this question Let's Discuss on Board"
    },
    {
        "question": "A beggar is standing . . . . . . . . the corner of the road.",
        "options": [
            {
                "option": "A.",
                "text": "on"
            },
            {
                "option": "B.",
                "text": "by"
            },
            {
                "option": "C.",
                "text": "at"
            },
            {
                "option": "D.",
                "text": "for"
            }
        ],
        "answer": "Option C",
        "solution": "Answer & Solution Answer: Option C No explanation is given for this question Let's Discuss on Board"
    },
    {
        "question": "You're always . . . . . . . . a hurry. You drive . . . . . . . . a tremendous speed.",
        "options": [
            {
                "option": "A.",
                "text": "for, at"
            },
            {
                "option": "B.",
                "text": "in, at"
            },
            {
                "option": "C.",
                "text": "on, with"
            },
            {
                "option": "D.",
                "text": "in, with"
            }
        ],
        "answer": "Option B",
        "solution": "Answer & Solution Answer: Option B No explanation is given for this question Let's Discuss on Board"
    },
    {
        "question": "He criticizes others, but is blind . . . . . . . . his own faults.",
        "options": [
            {
                "option": "A.",
                "text": "at"
            },
            {
                "option": "B.",
                "text": "of"
            },
            {
                "option": "C.",
                "text": "to"
            },
            {
                "option": "D.",
                "text": "over"
            }
        ],
        "answer": "Option C",
        "solution": "Answer & Solution Answer: Option C No explanation is given for this question Let's Discuss on Board"
    },
    {
        "question": "He is a man . . . . . . . . word.",
        "options": [
            {
                "option": "A.",
                "text": "of"
            },
            {
                "option": "B.",
                "text": "with"
            },
            {
                "option": "C.",
                "text": "for"
            },
            {
                "option": "D.",
                "text": "to"
            }
        ],
        "answer": "Option A",
        "solution": "Answer & Solution Answer: Option A No explanation is given for this question Let's Discuss on Board"
    },
    {
        "question": "When he finally came round . . . . . . . . writing the letter, he found his feelings were easier to express than he had expected.",
        "options": [
            {
                "option": "A.",
                "text": "in"
            },
            {
                "option": "B.",
                "text": "to"
            },
            {
                "option": "C.",
                "text": "with"
            },
            {
                "option": "D.",
                "text": "against"
            }
        ],
        "answer": "Option B",
        "solution": "Answer & Solution Answer: Option B No explanation is given for this question Let's Discuss on Board"
    },
    {
        "question": "The tree is . . . . . . . . the house. Which preposition is suitable to fill the blank?",
        "options": [
            {
                "option": "A.",
                "text": "across"
            },
            {
                "option": "B.",
                "text": "over"
            },
            {
                "option": "C.",
                "text": "behind"
            },
            {
                "option": "D.",
                "text": "None of the above"
            }
        ],
        "answer": "Option C",
        "solution": "Answer & Solution Answer: Option C No explanation is given for this question Let's Discuss on Board"
    },
    {
        "question": "Danish came out . . . . . . . . his office, looking tired and worried.",
        "options": [
            {
                "option": "A.",
                "text": "with"
            },
            {
                "option": "B.",
                "text": "from"
            },
            {
                "option": "C.",
                "text": "at"
            },
            {
                "option": "D.",
                "text": "of"
            }
        ],
        "answer": "Option D",
        "solution": "Answer & Solution Answer: Option D No explanation is given for this question Let's Discuss on Board"
    },
    {
        "question": "He saw his reflection . . . . . . . . the water.",
        "options": [
            {
                "option": "A.",
                "text": "on"
            },
            {
                "option": "B.",
                "text": "to"
            },
            {
                "option": "C.",
                "text": "in"
            },
            {
                "option": "D.",
                "text": "out"
            }
        ],
        "answer": "Option C",
        "solution": "Answer & Solution Answer: Option C No explanation is given for this question Let's Discuss on Board"
    },
    {
        "question": "My voice reverberated . . . . . . . . the walls of the castle.",
        "options": [
            {
                "option": "A.",
                "text": "from"
            },
            {
                "option": "B.",
                "text": "on"
            },
            {
                "option": "C.",
                "text": "in"
            },
            {
                "option": "D.",
                "text": "with"
            }
        ],
        "answer": "Option A",
        "solution": "Answer & Solution Answer: Option A No explanation is given for this question Let's Discuss on Board"
    },
    {
        "question": "The prisoner was bound . . . . . . . . the stake.",
        "options": [
            {
                "option": "A.",
                "text": "with"
            },
            {
                "option": "B.",
                "text": "of"
            },
            {
                "option": "C.",
                "text": "to"
            },
            {
                "option": "D.",
                "text": "at"
            }
        ],
        "answer": "Option C",
        "solution": "Answer & Solution Answer: Option C No explanation is given for this question Let's Discuss on Board"
    },
    {
        "question": "The store is open . . . . . . . . nine to eight.",
        "options": [
            {
                "option": "A.",
                "text": "during"
            },
            {
                "option": "B.",
                "text": "between"
            },
            {
                "option": "C.",
                "text": "from"
            },
            {
                "option": "D.",
                "text": "by"
            }
        ],
        "answer": "Option C",
        "solution": "Answer & Solution Answer: Option C No explanation is given for this question Let's Discuss on Board"
    },
    {
        "question": "I'm getting late . . . . . . . . office.",
        "options": [
            {
                "option": "A.",
                "text": "from"
            },
            {
                "option": "B.",
                "text": "for"
            },
            {
                "option": "C.",
                "text": "to"
            },
            {
                "option": "D.",
                "text": "in"
            }
        ],
        "answer": "Option B",
        "solution": "Answer & Solution Answer: Option B No explanation is given for this question Let's Discuss on Board"
    },
    {
        "question": "Fate smiles . . . . . . . . him in all his ventures.",
        "options": [
            {
                "option": "A.",
                "text": "upon"
            },
            {
                "option": "B.",
                "text": "at"
            },
            {
                "option": "C.",
                "text": "with"
            },
            {
                "option": "D.",
                "text": "for"
            }
        ],
        "answer": "Option A",
        "solution": "Answer & Solution Answer: Option A No explanation is given for this question Let's Discuss on Board"
    },
    {
        "question": "Vanraj has been sitting . . . . . . . . the dining table reading news papers . . . . . . . . two hours.",
        "options": [
            {
                "option": "A.",
                "text": "at, since"
            },
            {
                "option": "B.",
                "text": "at, for"
            },
            {
                "option": "C.",
                "text": "on, for"
            },
            {
                "option": "D.",
                "text": "on, since"
            }
        ],
        "answer": "Option B",
        "solution": "Answer & Solution Answer: Option B No explanation is given for this question Let's Discuss on Board"
    },
    {
        "question": "She was a devoted wife and looked . . . . . . . . her husband.",
        "options": [
            {
                "option": "A.",
                "text": "to"
            },
            {
                "option": "B.",
                "text": "at"
            },
            {
                "option": "C.",
                "text": "after"
            },
            {
                "option": "D.",
                "text": "upon"
            }
        ],
        "answer": "Option C",
        "solution": "Answer & Solution Answer: Option C No explanation is given for this question Let's Discuss on Board"
    },
    {
        "question": "I thought I saw your book . . . . . . . . the garage sitting o top of the shelves.",
        "options": [
            {
                "option": "A.",
                "text": "in"
            },
            {
                "option": "B.",
                "text": "on"
            },
            {
                "option": "C.",
                "text": "between"
            },
            {
                "option": "D.",
                "text": "None of the above"
            }
        ],
        "answer": "Option A",
        "solution": "Answer & Solution Answer: Option A No explanation is given for this question Let's Discuss on Board"
    },
    {
        "question": "At this age he is tired . . . . . . . . his life.",
        "options": [
            {
                "option": "A.",
                "text": "upon"
            },
            {
                "option": "B.",
                "text": "of"
            },
            {
                "option": "C.",
                "text": "from"
            },
            {
                "option": "D.",
                "text": "with"
            }
        ],
        "answer": "Option B",
        "solution": "Answer & Solution Answer: Option B No explanation is given for this question Let's Discuss on Board"
    },
    {
        "question": "I did not get on with them . . . . . . . . the word go.",
        "options": [
            {
                "option": "A.",
                "text": "about"
            },
            {
                "option": "B.",
                "text": "of"
            },
            {
                "option": "C.",
                "text": "from"
            },
            {
                "option": "D.",
                "text": "in"
            }
        ],
        "answer": "Option C",
        "solution": "Answer & Solution Answer: Option C No explanation is given for this question Let's Discuss on Board"
    },
    {
        "question": "\"Clean . . . . . . . . this mess, please,\" said the lady.",
        "options": [
            {
                "option": "A.",
                "text": "by"
            },
            {
                "option": "B.",
                "text": "on"
            },
            {
                "option": "C.",
                "text": "to"
            },
            {
                "option": "D.",
                "text": "up"
            }
        ],
        "answer": "Option D",
        "solution": "Answer & Solution Answer: Option D No explanation is given for this question Let's Discuss on Board"
    },
    {
        "question": "We have a solicitor who acts . . . . . . . . (represents) us in all business dealing.",
        "options": [
            {
                "option": "A.",
                "text": "about"
            },
            {
                "option": "B.",
                "text": "on"
            },
            {
                "option": "C.",
                "text": "out"
            },
            {
                "option": "D.",
                "text": "for"
            }
        ],
        "answer": "Option D",
        "solution": "Answer & Solution Answer: Option D No explanation is given for this question Let's Discuss on Board"
    },
    {
        "question": "Children . . . . . . . . the age of five can't be admitted to this school.",
        "options": [
            {
                "option": "A.",
                "text": "under"
            },
            {
                "option": "B.",
                "text": "at"
            },
            {
                "option": "C.",
                "text": "in"
            },
            {
                "option": "D.",
                "text": "with"
            }
        ],
        "answer": "Option A",
        "solution": "Answer & Solution Answer: Option A No explanation is given for this question Let's Discuss on Board"
    },
    {
        "question": "The problem . . . . . . . . housing . . . . . . . . India is a complex one.",
        "options": [
            {
                "option": "A.",
                "text": "of, in"
            },
            {
                "option": "B.",
                "text": "in, of"
            },
            {
                "option": "C.",
                "text": "for, in"
            },
            {
                "option": "D.",
                "text": "about, in"
            }
        ],
        "answer": "Option A",
        "solution": "Answer & Solution Answer: Option A No explanation is given for this question Let's Discuss on Board"
    },
    {
        "question": "Who's the blonde girl . . . . . . . . the first raw?",
        "options": [
            {
                "option": "A.",
                "text": "in"
            },
            {
                "option": "B.",
                "text": "on"
            },
            {
                "option": "C.",
                "text": "at"
            },
            {
                "option": "D.",
                "text": "over"
            }
        ],
        "answer": "Option A",
        "solution": "Answer & Solution Answer: Option A No explanation is given for this question Let's Discuss on Board"
    },
    {
        "question": "He was embarrassed because everybody was laughing . . . . . . . . him?",
        "options": [
            {
                "option": "A.",
                "text": "of"
            },
            {
                "option": "B.",
                "text": "in"
            },
            {
                "option": "C.",
                "text": "about"
            },
            {
                "option": "D.",
                "text": "at"
            }
        ],
        "answer": "Option D",
        "solution": "Answer & Solution Answer: Option D No explanation is given for this question Let's Discuss on Board"
    },
    {
        "question": "Mr. Rajendran is still . . . . . . . . leave.",
        "options": [
            {
                "option": "A.",
                "text": "on"
            },
            {
                "option": "B.",
                "text": "in"
            },
            {
                "option": "C.",
                "text": "to"
            },
            {
                "option": "D.",
                "text": "by"
            }
        ],
        "answer": "Option A",
        "solution": "Answer & Solution Answer: Option A No explanation is given for this question Let's Discuss on Board"
    },
    {
        "question": "Don't point . . . . . . . . my mistakes.",
        "options": [
            {
                "option": "A.",
                "text": "in"
            },
            {
                "option": "B.",
                "text": "at"
            },
            {
                "option": "C.",
                "text": "out"
            },
            {
                "option": "D.",
                "text": "for"
            }
        ],
        "answer": "Option C",
        "solution": "Answer & Solution Answer: Option C No explanation is given for this question Let's Discuss on Board"
    },
    {
        "question": "The car stopped . . . . . . . . the zebra crossing to allow the pedestrians to cross.",
        "options": [
            {
                "option": "A.",
                "text": "at"
            },
            {
                "option": "B.",
                "text": "in"
            },
            {
                "option": "C.",
                "text": "on"
            },
            {
                "option": "D.",
                "text": "over"
            }
        ],
        "answer": "Option A",
        "solution": "Answer & Solution Answer: Option A No explanation is given for this question Let's Discuss on Board"
    },
    {
        "question": "We live . . . . . . . . this address.",
        "options": [
            {
                "option": "A.",
                "text": "on"
            },
            {
                "option": "B.",
                "text": "in"
            },
            {
                "option": "C.",
                "text": "at"
            },
            {
                "option": "D.",
                "text": "None of the above"
            }
        ],
        "answer": "Option C",
        "solution": "Answer & Solution Answer: Option C No explanation is given for this question Let's Discuss on Board"
    },
    {
        "question": "The man has been . . . . . . . . jail once or twice.",
        "options": [
            {
                "option": "A.",
                "text": "in"
            },
            {
                "option": "B.",
                "text": "from"
            },
            {
                "option": "C.",
                "text": "on"
            },
            {
                "option": "D.",
                "text": "under"
            }
        ],
        "answer": "Option A",
        "solution": "Answer & Solution Answer: Option A No explanation is given for this question Let's Discuss on Board"
    },
    {
        "question": "I saw you dancing . . . . . . . . party.",
        "options": [
            {
                "option": "A.",
                "text": "at"
            },
            {
                "option": "B.",
                "text": "at a"
            },
            {
                "option": "C.",
                "text": "at the"
            },
            {
                "option": "D.",
                "text": "in"
            }
        ],
        "answer": "Option C",
        "solution": "Answer & Solution Answer: Option C No explanation is given for this question Let's Discuss on Board"
    },
    {
        "question": "Doni appeared settled . . . . . . . . the crease?",
        "options": [
            {
                "option": "A.",
                "text": "on"
            },
            {
                "option": "B.",
                "text": "at"
            },
            {
                "option": "C.",
                "text": "in"
            },
            {
                "option": "D.",
                "text": "none"
            }
        ],
        "answer": "Option B",
        "solution": "Answer & Solution Answer: Option B No explanation is given for this question Let's Discuss on Board"
    },
    {
        "question": "He went to Delhi . . . . . . . . train.",
        "options": [
            {
                "option": "A.",
                "text": "to"
            },
            {
                "option": "B.",
                "text": "by"
            },
            {
                "option": "C.",
                "text": "from"
            },
            {
                "option": "D.",
                "text": "with"
            }
        ],
        "answer": "Option B",
        "solution": "Answer & Solution Answer: Option B No explanation is given for this question Let's Discuss on Board"
    },
    {
        "question": "You should not include . . . . . . . . idle talks.",
        "options": [
            {
                "option": "A.",
                "text": "in"
            },
            {
                "option": "B.",
                "text": "about"
            },
            {
                "option": "C.",
                "text": "over"
            },
            {
                "option": "D.",
                "text": "on"
            }
        ],
        "answer": "Option A",
        "solution": "Answer & Solution Answer: Option A No explanation is given for this question Let's Discuss on Board"
    },
    {
        "question": "He writes . . . . . . . . ink.",
        "options": [
            {
                "option": "A.",
                "text": "with"
            },
            {
                "option": "B.",
                "text": "in"
            },
            {
                "option": "C.",
                "text": "for"
            },
            {
                "option": "D.",
                "text": "on"
            }
        ],
        "answer": "Option B",
        "solution": "Answer & Solution Answer: Option B No explanation is given for this question Let's Discuss on Board"
    },
    {
        "question": "Write some lines . . . . . . . . the nature.",
        "options": [
            {
                "option": "A.",
                "text": "with"
            },
            {
                "option": "B.",
                "text": "from"
            },
            {
                "option": "C.",
                "text": "above"
            },
            {
                "option": "D.",
                "text": "about"
            }
        ],
        "answer": "Option D",
        "solution": "Answer & Solution Answer: Option D No explanation is given for this question Let's Discuss on Board"
    },
    {
        "question": "Sana filled the glass . . . . . . . . water.",
        "options": [
            {
                "option": "A.",
                "text": "with"
            },
            {
                "option": "B.",
                "text": "of"
            },
            {
                "option": "C.",
                "text": "from"
            },
            {
                "option": "D.",
                "text": "by"
            }
        ],
        "answer": "Option A",
        "solution": "Answer & Solution Answer: Option A No explanation is given for this question Let's Discuss on Board"
    }
]